<?xml version="1.0" encoding="UTF-8"?>

<!-- generated on 2024-04-02 15:02:37 by Eclipse SUMO sumo Version 1.19.0
<configuration xmlns:xsi="http://www.w3.org/2001/XMLSchema-instance" xsi:noNamespaceSchemaLocation="http://sumo.dlr.de/xsd/sumoConfiguration.xsd">

    <input>
        <net-file value="sumo_network/example42.net.xml"/>
        <route-files value="sumo_network/example42.rou.xml,sumo_network/bus.rou.xml,sumo_network/pedestrian.rou.xml"/>
        <additional-files value="sumo_network/busstops_def.add.xml,sumo_network/det_e3.add.xml,sumo_network/det_e2.add.xml,sumo_network/edgelane_dump.add.xml,sumo_network/signal-timing-dial.xml"/>
    </input>

    <output>
        <write-license value="false"/>
        <output-prefix value="OUTPUT-"/>
        <precision value="2"/>
        <human-readable-time value="false"/>
        <emission-output value="sumo_network/output/data_emission.xml"/>
        <emission-output.precision value="2"/>
        <queue-output value="sumo_network/output/data_Queue.xml"/>
        <queue-output.period value="300"/>
        <summary-output value="sumo_network/output/data_summary.xml"/>
        <summary-output.period value="300"/>
        <person-summary-output value="sumo_network/output/data_person_summary.xml"/>
        <personinfo-output value="sumo_network/output/data_personinfo.xml"/>
        <collision-output value="sumo_network/output/data_collision.xml"/>
        <edgedata-output value="sumo_network/output/data_edges.xml"/>
        <lanedata-output value="sumo_network/output/data_lanes.xml"/>
        <statistic-output value="sumo_network/output/data_statistic.xml"/>
    </output>

    <time>
        <begin value="0"/>
        <end value="3600"/>
        <step-length value="1"/>
    </time>

    <processing>
        <no-internal-links value="false"/>
        <ignore-route-errors value="true"/>
        <collision.action value="teleport"/>
        <intermodal-collision.action value="warn"/>
        <collision.stoptime value="0"/>
        <intermodal-collision.stoptime value="0"/>
        <collision.check-junctions value="false"/>
        <max-num-vehicles value="-1"/>
        <max-num-teleports value="-1"/>
        <time-to-teleport value="300"/>
        <time-to-teleport.remove value="false"/>
        <waiting-time-memory value="100"/>
        <max-depart-delay value="-1"/>
        <random-depart-offset value="0"/>
        <lanechange.duration value="0"/>
        <lanechange.overtake-right value="false"/>
        <tls.all-off value="false"/>
        <tls.yellow.min-decel value="3"/>
    </processing>

    <routing>
        <routing-algorithm value="dijkstra"/>
    </routing>

    <report>
        <verbose value="true"/>
        <no-warnings value="true"/>
        <log value="sumo_network/output/data_log.xml"/>
        <no-step-log value="true"/>
        <step-log.period value="300"/>
    </report>

    <emissions>
        <device.emissions.period value="300"/>
    </emissions>

    <traci_server>
        <remote-port value="8813"/>
    </traci_server>

    <mesoscopic>
        <mesosim value="false"/>
    </mesoscopic>

    <random_number>
        <random value="false"/>
        <seed value="23423"/>
    </random_number>

    <gui_only>
        <gui-settings-file value="sumo_network/viewsettings.xml"/>
        <start value="true"/>
        <demo value="false"/>
        <window-size value="800,600"/>
        <window-pos value="100,100"/>
    </gui_only>

</configuration>
-->

<detector xmlns:xsi="http://www.w3.org/2001/XMLSchema-instance" xsi:noNamespaceSchemaLocation="http://sumo.dlr.de/xsd/det_e2_file.xsd">
   <interval begin="0.00" end="300.00" id="yuanlinlu_west_entry0" sampledSeconds="0.00" nVehEntered="0" nVehLeft="0" nVehSeen="0" meanSpeed="-1.00" meanTimeLoss="-1.00" meanOccupancy="0.00" maxOccupancy="0.00" meanMaxJamLengthInVehicles="0.00" meanMaxJamLengthInMeters="0.00" maxJamLengthInVehicles="0" maxJamLengthInMeters="0.00" jamLengthInVehiclesSum="0" jamLengthInMetersSum="0.00" meanHaltingDuration="0.00" maxHaltingDuration="0.00" haltingDurationSum="0.00" meanIntervalHaltingDuration="0.00" maxIntervalHaltingDuration="0.00" intervalHaltingDurationSum="0.00" startedHalts="0.00" meanVehicleNumber="0.00" maxVehicleNumber="0" />
   <interval begin="0.00" end="300.00" id="yuanlinlu_west_entry1" sampledSeconds="844.29" nVehEntered="27" nVehLeft="24" nVehSeen="27" meanSpeed="8.06" meanTimeLoss="11.55" meanOccupancy="4.58" maxOccupancy="9.43" meanMaxJamLengthInVehicles="0.56" meanMaxJamLengthInMeters="12.51" maxJamLengthInVehicles="3" maxJamLengthInMeters="157.74" jamLengthInVehiclesSum="169" jamLengthInMetersSum="3753.01" meanHaltingDuration="16.36" maxHaltingDuration="61.00" haltingDurationSum="180.00" meanIntervalHaltingDuration="16.36" maxIntervalHaltingDuration="61.00" intervalHaltingDurationSum="180.00" startedHalts="12.00" meanVehicleNumber="2.84" maxVehicleNumber="5" />
   <interval begin="0.00" end="300.00" id="yuanlinlu_west_entry2" sampledSeconds="7003.28" nVehEntered="70" nVehLeft="32" nVehSeen="70" meanSpeed="2.33" meanTimeLoss="82.59" meanOccupancy="33.95" maxOccupancy="58.41" meanMaxJamLengthInVehicles="11.97" meanMaxJamLengthInMeters="92.72" maxJamLengthInVehicles="27" maxJamLengthInMeters="214.28" jamLengthInVehiclesSum="4392" jamLengthInMetersSum="33688.77" meanHaltingDuration="16.32" maxHaltingDuration="100.00" haltingDurationSum="4650.00" meanIntervalHaltingDuration="16.32" maxIntervalHaltingDuration="100.00" intervalHaltingDurationSum="4650.00" startedHalts="286.00" meanVehicleNumber="23.39" maxVehicleNumber="41" />
   <interval begin="0.00" end="300.00" id="yuanlinlu_west_entry3" sampledSeconds="862.68" nVehEntered="16" nVehLeft="14" nVehSeen="16" meanSpeed="5.68" meanTimeLoss="30.22" meanOccupancy="4.37" maxOccupancy="10.84" meanMaxJamLengthInVehicles="1.29" meanMaxJamLengthInMeters="9.60" maxJamLengthInVehicles="6" maxJamLengthInMeters="46.83" jamLengthInVehiclesSum="386" jamLengthInMetersSum="2879.66" meanHaltingDuration="49.25" maxHaltingDuration="91.00" haltingDurationSum="394.00" meanIntervalHaltingDuration="49.25" maxIntervalHaltingDuration="91.00" intervalHaltingDurationSum="394.00" startedHalts="8.00" meanVehicleNumber="2.89" maxVehicleNumber="7" />
   <interval begin="0.00" end="300.00" id="yuanlinlu_west_exit0" sampledSeconds="0.00" nVehEntered="0" nVehLeft="0" nVehSeen="0" meanSpeed="-1.00" meanTimeLoss="-1.00" meanOccupancy="0.00" maxOccupancy="0.00" meanMaxJamLengthInVehicles="0.00" meanMaxJamLengthInMeters="0.00" maxJamLengthInVehicles="0" maxJamLengthInMeters="0.00" jamLengthInVehiclesSum="0" jamLengthInMetersSum="0.00" meanHaltingDuration="0.00" maxHaltingDuration="0.00" haltingDurationSum="0.00" meanIntervalHaltingDuration="0.00" maxIntervalHaltingDuration="0.00" intervalHaltingDurationSum="0.00" startedHalts="0.00" meanVehicleNumber="0.00" maxVehicleNumber="0" />
   <interval begin="0.00" end="300.00" id="yuanlinlu_west_exit1" sampledSeconds="105.37" nVehEntered="6" nVehLeft="6" nVehSeen="6" meanSpeed="12.06" meanTimeLoss="1.15" meanOccupancy="0.47" maxOccupancy="4.15" meanMaxJamLengthInVehicles="0.00" meanMaxJamLengthInMeters="0.00" maxJamLengthInVehicles="0" maxJamLengthInMeters="0.00" jamLengthInVehiclesSum="0" jamLengthInMetersSum="0.00" meanHaltingDuration="0.00" maxHaltingDuration="0.00" haltingDurationSum="0.00" meanIntervalHaltingDuration="0.00" maxIntervalHaltingDuration="0.00" intervalHaltingDurationSum="0.00" startedHalts="0.00" meanVehicleNumber="0.36" maxVehicleNumber="3" />
   <interval begin="0.00" end="300.00" id="yuanlinlu_west_exit2" sampledSeconds="102.69" nVehEntered="9" nVehLeft="5" nVehSeen="9" meanSpeed="12.63" meanTimeLoss="0.64" meanOccupancy="0.48" maxOccupancy="5.53" meanMaxJamLengthInVehicles="0.00" meanMaxJamLengthInMeters="0.00" maxJamLengthInVehicles="0" maxJamLengthInMeters="0.00" jamLengthInVehiclesSum="0" jamLengthInMetersSum="0.00" meanHaltingDuration="0.00" maxHaltingDuration="0.00" haltingDurationSum="0.00" meanIntervalHaltingDuration="0.00" maxIntervalHaltingDuration="0.00" intervalHaltingDurationSum="0.00" startedHalts="0.00" meanVehicleNumber="0.35" maxVehicleNumber="4" />
   <interval begin="0.00" end="300.00" id="yuanlinlu_west_exit3" sampledSeconds="21.59" nVehEntered="1" nVehLeft="1" nVehSeen="1" meanSpeed="13.76" meanTimeLoss="1.14" meanOccupancy="0.10" maxOccupancy="1.38" meanMaxJamLengthInVehicles="0.00" meanMaxJamLengthInMeters="0.00" maxJamLengthInVehicles="0" maxJamLengthInMeters="0.00" jamLengthInVehiclesSum="0" jamLengthInMetersSum="0.00" meanHaltingDuration="0.00" maxHaltingDuration="0.00" haltingDurationSum="0.00" meanIntervalHaltingDuration="0.00" maxIntervalHaltingDuration="0.00" intervalHaltingDurationSum="0.00" startedHalts="0.00" meanVehicleNumber="0.07" maxVehicleNumber="1" />
   <interval begin="0.00" end="300.00" id="yuanlinlu_east_entry0" sampledSeconds="0.00" nVehEntered="0" nVehLeft="0" nVehSeen="0" meanSpeed="-1.00" meanTimeLoss="-1.00" meanOccupancy="0.00" maxOccupancy="0.00" meanMaxJamLengthInVehicles="0.00" meanMaxJamLengthInMeters="0.00" maxJamLengthInVehicles="0" maxJamLengthInMeters="0.00" jamLengthInVehiclesSum="0" jamLengthInMetersSum="0.00" meanHaltingDuration="0.00" maxHaltingDuration="0.00" haltingDurationSum="0.00" meanIntervalHaltingDuration="0.00" maxIntervalHaltingDuration="0.00" intervalHaltingDurationSum="0.00" startedHalts="0.00" meanVehicleNumber="0.00" maxVehicleNumber="0" />
   <interval begin="0.00" end="300.00" id="yuanlinlu_east_entry1" sampledSeconds="805.27" nVehEntered="20" nVehLeft="19" nVehSeen="20" meanSpeed="4.38" meanTimeLoss="26.19" meanOccupancy="4.75" maxOccupancy="9.83" meanMaxJamLengthInVehicles="1.35" meanMaxJamLengthInMeters="14.43" maxJamLengthInVehicles="6" maxJamLengthInMeters="158.14" jamLengthInVehiclesSum="420" jamLengthInMetersSum="4487.11" meanHaltingDuration="43.00" maxHaltingDuration="96.00" haltingDurationSum="430.00" meanIntervalHaltingDuration="43.00" maxIntervalHaltingDuration="96.00" intervalHaltingDurationSum="430.00" startedHalts="11.00" meanVehicleNumber="2.71" maxVehicleNumber="6" />
   <interval begin="0.00" end="300.00" id="yuanlinlu_east_entry2" sampledSeconds="6619.58" nVehEntered="59" nVehLeft="20" nVehSeen="59" meanSpeed="1.66" meanTimeLoss="98.13" meanOccupancy="35.75" maxOccupancy="66.40" meanMaxJamLengthInVehicles="17.39" meanMaxJamLengthInMeters="133.78" maxJamLengthInVehicles="41" maxJamLengthInMeters="317.24" jamLengthInVehiclesSum="5225" jamLengthInMetersSum="40195.18" meanHaltingDuration="65.51" maxHaltingDuration="127.00" haltingDurationSum="5306.00" meanIntervalHaltingDuration="65.51" maxIntervalHaltingDuration="127.00" intervalHaltingDurationSum="5306.00" startedHalts="81.00" meanVehicleNumber="22.09" maxVehicleNumber="41" />
   <interval begin="0.00" end="300.00" id="yuanlinlu_east_entry3" sampledSeconds="103.20" nVehEntered="1" nVehLeft="1" nVehSeen="1" meanSpeed="3.15" meanTimeLoss="78.07" meanOccupancy="0.52" maxOccupancy="1.54" meanMaxJamLengthInVehicles="0.24" meanMaxJamLengthInMeters="1.18" maxJamLengthInVehicles="1" maxJamLengthInMeters="5.00" jamLengthInVehiclesSum="71" jamLengthInMetersSum="355.00" meanHaltingDuration="72.00" maxHaltingDuration="72.00" haltingDurationSum="72.00" meanIntervalHaltingDuration="72.00" maxIntervalHaltingDuration="72.00" intervalHaltingDurationSum="72.00" startedHalts="1.00" meanVehicleNumber="0.35" maxVehicleNumber="1" />
   <interval begin="0.00" end="300.00" id="yuanlinlu_east_exit0" sampledSeconds="0.00" nVehEntered="0" nVehLeft="0" nVehSeen="0" meanSpeed="-1.00" meanTimeLoss="-1.00" meanOccupancy="0.00" maxOccupancy="0.00" meanMaxJamLengthInVehicles="0.00" meanMaxJamLengthInMeters="0.00" maxJamLengthInVehicles="0" maxJamLengthInMeters="0.00" jamLengthInVehiclesSum="0" jamLengthInMetersSum="0.00" meanHaltingDuration="0.00" maxHaltingDuration="0.00" haltingDurationSum="0.00" meanIntervalHaltingDuration="0.00" maxIntervalHaltingDuration="0.00" intervalHaltingDurationSum="0.00" startedHalts="0.00" meanVehicleNumber="0.00" maxVehicleNumber="0" />
   <interval begin="0.00" end="300.00" id="yuanlinlu_east_exit1" sampledSeconds="122.32" nVehEntered="8" nVehLeft="7" nVehSeen="8" meanSpeed="11.56" meanTimeLoss="1.20" meanOccupancy="0.62" maxOccupancy="4.61" meanMaxJamLengthInVehicles="0.00" meanMaxJamLengthInMeters="0.00" maxJamLengthInVehicles="0" maxJamLengthInMeters="0.00" jamLengthInVehiclesSum="0" jamLengthInMetersSum="0.00" meanHaltingDuration="0.00" maxHaltingDuration="0.00" haltingDurationSum="0.00" meanIntervalHaltingDuration="0.00" maxIntervalHaltingDuration="0.00" intervalHaltingDurationSum="0.00" startedHalts="0.00" meanVehicleNumber="0.42" maxVehicleNumber="3" />
   <interval begin="0.00" end="300.00" id="yuanlinlu_east_exit2" sampledSeconds="174.77" nVehEntered="10" nVehLeft="10" nVehSeen="10" meanSpeed="12.98" meanTimeLoss="1.32" meanOccupancy="0.92" maxOccupancy="6.14" meanMaxJamLengthInVehicles="0.00" meanMaxJamLengthInMeters="0.00" maxJamLengthInVehicles="0" maxJamLengthInMeters="0.00" jamLengthInVehiclesSum="0" jamLengthInMetersSum="0.00" meanHaltingDuration="0.00" maxHaltingDuration="0.00" haltingDurationSum="0.00" meanIntervalHaltingDuration="0.00" maxIntervalHaltingDuration="0.00" intervalHaltingDurationSum="0.00" startedHalts="0.00" meanVehicleNumber="0.59" maxVehicleNumber="4" />
   <interval begin="0.00" end="300.00" id="yuanlinlu_east_exit3" sampledSeconds="112.52" nVehEntered="5" nVehLeft="5" nVehSeen="5" meanSpeed="11.12" meanTimeLoss="2.43" meanOccupancy="0.60" maxOccupancy="5.25" meanMaxJamLengthInVehicles="0.00" meanMaxJamLengthInMeters="0.00" maxJamLengthInVehicles="0" maxJamLengthInMeters="0.00" jamLengthInVehiclesSum="0" jamLengthInMetersSum="0.00" meanHaltingDuration="0.00" maxHaltingDuration="0.00" haltingDurationSum="0.00" meanIntervalHaltingDuration="0.00" maxIntervalHaltingDuration="0.00" intervalHaltingDurationSum="0.00" startedHalts="0.00" meanVehicleNumber="0.38" maxVehicleNumber="3" />
   <interval begin="0.00" end="300.00" id="yuanlinlu_west_mid_entry0" sampledSeconds="0.00" nVehEntered="0" nVehLeft="0" nVehSeen="0" meanSpeed="-1.00" meanTimeLoss="-1.00" meanOccupancy="0.00" maxOccupancy="0.00" meanMaxJamLengthInVehicles="0.00" meanMaxJamLengthInMeters="0.00" maxJamLengthInVehicles="0" maxJamLengthInMeters="0.00" jamLengthInVehiclesSum="0" jamLengthInMetersSum="0.00" meanHaltingDuration="0.00" maxHaltingDuration="0.00" haltingDurationSum="0.00" meanIntervalHaltingDuration="0.00" maxIntervalHaltingDuration="0.00" intervalHaltingDurationSum="0.00" startedHalts="0.00" meanVehicleNumber="0.00" maxVehicleNumber="0" />
   <interval begin="0.00" end="300.00" id="yuanlinlu_west_mid_entry1" sampledSeconds="58.42" nVehEntered="4" nVehLeft="4" nVehSeen="4" meanSpeed="9.86" meanTimeLoss="1.38" meanOccupancy="0.36" maxOccupancy="4.11" meanMaxJamLengthInVehicles="0.00" meanMaxJamLengthInMeters="0.00" maxJamLengthInVehicles="0" maxJamLengthInMeters="0.00" jamLengthInVehiclesSum="0" jamLengthInMetersSum="0.00" meanHaltingDuration="0.00" maxHaltingDuration="0.00" haltingDurationSum="0.00" meanIntervalHaltingDuration="0.00" maxIntervalHaltingDuration="0.00" intervalHaltingDurationSum="0.00" startedHalts="0.00" meanVehicleNumber="0.20" maxVehicleNumber="3" />
   <interval begin="0.00" end="300.00" id="yuanlinlu_west_mid_entry2" sampledSeconds="1813.26" nVehEntered="32" nVehLeft="11" nVehSeen="32" meanSpeed="3.70" meanTimeLoss="40.22" meanOccupancy="9.15" maxOccupancy="31.29" meanMaxJamLengthInVehicles="3.96" meanMaxJamLengthInMeters="29.63" maxJamLengthInVehicles="17" maxJamLengthInMeters="134.12" jamLengthInVehiclesSum="1188" jamLengthInMetersSum="8889.73" meanHaltingDuration="63.53" maxHaltingDuration="125.00" haltingDurationSum="1207.00" meanIntervalHaltingDuration="63.53" maxIntervalHaltingDuration="125.00" intervalHaltingDurationSum="1207.00" startedHalts="19.00" meanVehicleNumber="6.10" maxVehicleNumber="21" />
   <interval begin="0.00" end="300.00" id="yuanlinlu_west_mid_entry3" sampledSeconds="212.02" nVehEntered="10" nVehLeft="9" nVehSeen="10" meanSpeed="9.40" meanTimeLoss="6.69" meanOccupancy="0.99" maxOccupancy="4.11" meanMaxJamLengthInVehicles="0.18" meanMaxJamLengthInMeters="0.92" maxJamLengthInVehicles="1" maxJamLengthInMeters="5.00" jamLengthInVehiclesSum="55" jamLengthInMetersSum="275.00" meanHaltingDuration="56.00" maxHaltingDuration="56.00" haltingDurationSum="56.00" meanIntervalHaltingDuration="56.00" maxIntervalHaltingDuration="56.00" intervalHaltingDurationSum="56.00" startedHalts="1.00" meanVehicleNumber="0.72" maxVehicleNumber="4" />
   <interval begin="0.00" end="300.00" id="yuanlinlu_west_mid_exit0" sampledSeconds="0.00" nVehEntered="0" nVehLeft="0" nVehSeen="0" meanSpeed="-1.00" meanTimeLoss="-1.00" meanOccupancy="0.00" maxOccupancy="0.00" meanMaxJamLengthInVehicles="0.00" meanMaxJamLengthInMeters="0.00" maxJamLengthInVehicles="0" maxJamLengthInMeters="0.00" jamLengthInVehiclesSum="0" jamLengthInMetersSum="0.00" meanHaltingDuration="0.00" maxHaltingDuration="0.00" haltingDurationSum="0.00" meanIntervalHaltingDuration="0.00" maxIntervalHaltingDuration="0.00" intervalHaltingDurationSum="0.00" startedHalts="0.00" meanVehicleNumber="0.00" maxVehicleNumber="0" />
   <interval begin="0.00" end="300.00" id="yuanlinlu_west_mid_exit1" sampledSeconds="266.95" nVehEntered="11" nVehLeft="11" nVehSeen="11" meanSpeed="7.33" meanTimeLoss="10.13" meanOccupancy="1.21" maxOccupancy="4.11" meanMaxJamLengthInVehicles="0.29" meanMaxJamLengthInMeters="1.43" maxJamLengthInVehicles="1" maxJamLengthInMeters="5.00" jamLengthInVehiclesSum="86" jamLengthInMetersSum="430.00" meanHaltingDuration="44.00" maxHaltingDuration="82.00" haltingDurationSum="88.00" meanIntervalHaltingDuration="44.00" maxIntervalHaltingDuration="82.00" intervalHaltingDurationSum="88.00" startedHalts="2.00" meanVehicleNumber="0.90" maxVehicleNumber="3" />
   <interval begin="0.00" end="300.00" id="yuanlinlu_west_mid_exit2" sampledSeconds="373.98" nVehEntered="11" nVehLeft="11" nVehSeen="11" meanSpeed="6.81" meanTimeLoss="16.13" meanOccupancy="1.70" maxOccupancy="5.49" meanMaxJamLengthInVehicles="0.44" meanMaxJamLengthInMeters="2.86" maxJamLengthInVehicles="4" maxJamLengthInMeters="27.58" jamLengthInVehiclesSum="133" jamLengthInMetersSum="857.35" meanHaltingDuration="20.00" maxHaltingDuration="38.00" haltingDurationSum="140.00" meanIntervalHaltingDuration="20.00" maxIntervalHaltingDuration="38.00" intervalHaltingDurationSum="140.00" startedHalts="7.00" meanVehicleNumber="1.27" maxVehicleNumber="4" />
   <interval begin="0.00" end="300.00" id="yuanlinlu_west_mid_exit3" sampledSeconds="122.11" nVehEntered="6" nVehLeft="6" nVehSeen="6" meanSpeed="9.22" meanTimeLoss="6.26" meanOccupancy="0.65" maxOccupancy="4.11" meanMaxJamLengthInVehicles="0.08" meanMaxJamLengthInMeters="0.59" maxJamLengthInVehicles="1" maxJamLengthInMeters="7.10" jamLengthInVehiclesSum="25" jamLengthInMetersSum="177.50" meanHaltingDuration="26.00" maxHaltingDuration="26.00" haltingDurationSum="26.00" meanIntervalHaltingDuration="26.00" maxIntervalHaltingDuration="26.00" intervalHaltingDurationSum="26.00" startedHalts="1.00" meanVehicleNumber="0.42" maxVehicleNumber="3" />
   <interval begin="0.00" end="300.00" id="yuanlinlu_east_mid_entry0" sampledSeconds="0.00" nVehEntered="0" nVehLeft="0" nVehSeen="0" meanSpeed="-1.00" meanTimeLoss="-1.00" meanOccupancy="0.00" maxOccupancy="0.00" meanMaxJamLengthInVehicles="0.00" meanMaxJamLengthInMeters="0.00" maxJamLengthInVehicles="0" maxJamLengthInMeters="0.00" jamLengthInVehiclesSum="0" jamLengthInMetersSum="0.00" meanHaltingDuration="0.00" maxHaltingDuration="0.00" haltingDurationSum="0.00" meanIntervalHaltingDuration="0.00" maxIntervalHaltingDuration="0.00" intervalHaltingDurationSum="0.00" startedHalts="0.00" meanVehicleNumber="0.00" maxVehicleNumber="0" />
   <interval begin="0.00" end="300.00" id="yuanlinlu_east_mid_entry1" sampledSeconds="169.59" nVehEntered="10" nVehLeft="10" nVehSeen="10" meanSpeed="5.43" meanTimeLoss="9.34" meanOccupancy="1.25" maxOccupancy="4.66" meanMaxJamLengthInVehicles="0.25" meanMaxJamLengthInMeters="2.73" maxJamLengthInVehicles="2" maxJamLengthInMeters="12.62" jamLengthInVehiclesSum="76" jamLengthInMetersSum="819.65" meanHaltingDuration="8.50" maxHaltingDuration="9.00" haltingDurationSum="17.00" meanIntervalHaltingDuration="8.50" maxIntervalHaltingDuration="9.00" intervalHaltingDurationSum="17.00" startedHalts="3.00" meanVehicleNumber="0.58" maxVehicleNumber="2" />
   <interval begin="0.00" end="300.00" id="yuanlinlu_east_mid_entry2" sampledSeconds="1736.47" nVehEntered="22" nVehLeft="9" nVehSeen="22" meanSpeed="2.87" meanTimeLoss="61.48" meanOccupancy="8.96" maxOccupancy="21.69" meanMaxJamLengthInVehicles="4.26" meanMaxJamLengthInMeters="33.45" maxJamLengthInVehicles="12" maxJamLengthInMeters="96.64" jamLengthInVehiclesSum="1279" jamLengthInMetersSum="10035.66" meanHaltingDuration="99.38" maxHaltingDuration="131.00" haltingDurationSum="1292.00" meanIntervalHaltingDuration="99.38" maxIntervalHaltingDuration="131.00" intervalHaltingDurationSum="1292.00" startedHalts="13.00" meanVehicleNumber="5.82" maxVehicleNumber="14" />
   <interval begin="0.00" end="300.00" id="yuanlinlu_east_mid_entry3" sampledSeconds="193.02" nVehEntered="8" nVehLeft="7" nVehSeen="8" meanSpeed="9.64" meanTimeLoss="7.04" meanOccupancy="0.87" maxOccupancy="5.48" meanMaxJamLengthInVehicles="0.12" meanMaxJamLengthInMeters="0.62" maxJamLengthInVehicles="1" maxJamLengthInMeters="5.00" jamLengthInVehiclesSum="37" jamLengthInMetersSum="185.00" meanHaltingDuration="19.50" maxHaltingDuration="36.00" haltingDurationSum="39.00" meanIntervalHaltingDuration="19.50" maxIntervalHaltingDuration="36.00" intervalHaltingDurationSum="39.00" startedHalts="2.00" meanVehicleNumber="0.66" maxVehicleNumber="4" />
   <interval begin="0.00" end="300.00" id="yuanlinlu_east_mid_exit0" sampledSeconds="0.00" nVehEntered="0" nVehLeft="0" nVehSeen="0" meanSpeed="-1.00" meanTimeLoss="-1.00" meanOccupancy="0.00" maxOccupancy="0.00" meanMaxJamLengthInVehicles="0.00" meanMaxJamLengthInMeters="0.00" maxJamLengthInVehicles="0" maxJamLengthInMeters="0.00" jamLengthInVehiclesSum="0" jamLengthInMetersSum="0.00" meanHaltingDuration="0.00" maxHaltingDuration="0.00" haltingDurationSum="0.00" meanIntervalHaltingDuration="0.00" maxIntervalHaltingDuration="0.00" intervalHaltingDurationSum="0.00" startedHalts="0.00" meanVehicleNumber="0.00" maxVehicleNumber="0" />
   <interval begin="0.00" end="300.00" id="yuanlinlu_east_mid_exit1" sampledSeconds="173.61" nVehEntered="8" nVehLeft="7" nVehSeen="8" meanSpeed="6.15" meanTimeLoss="9.26" meanOccupancy="1.52" maxOccupancy="6.03" meanMaxJamLengthInVehicles="0.20" meanMaxJamLengthInMeters="2.44" maxJamLengthInVehicles="1" maxJamLengthInMeters="12.00" jamLengthInVehiclesSum="61" jamLengthInMetersSum="732.00" meanHaltingDuration="62.00" maxHaltingDuration="62.00" haltingDurationSum="62.00" meanIntervalHaltingDuration="62.00" maxIntervalHaltingDuration="62.00" intervalHaltingDurationSum="62.00" startedHalts="1.00" meanVehicleNumber="0.59" maxVehicleNumber="3" />
   <interval begin="0.00" end="300.00" id="yuanlinlu_east_mid_exit2" sampledSeconds="329.35" nVehEntered="12" nVehLeft="10" nVehSeen="12" meanSpeed="6.45" meanTimeLoss="14.74" meanOccupancy="1.51" maxOccupancy="5.48" meanMaxJamLengthInVehicles="0.48" meanMaxJamLengthInMeters="3.05" maxJamLengthInVehicles="4" maxJamLengthInMeters="27.56" jamLengthInVehiclesSum="145" jamLengthInMetersSum="913.96" meanHaltingDuration="30.00" maxHaltingDuration="37.00" haltingDurationSum="150.00" meanIntervalHaltingDuration="30.00" maxIntervalHaltingDuration="37.00" intervalHaltingDurationSum="150.00" startedHalts="5.00" meanVehicleNumber="1.11" maxVehicleNumber="4" />
   <interval begin="0.00" end="300.00" id="yuanlinlu_east_mid_exit3" sampledSeconds="78.11" nVehEntered="7" nVehLeft="6" nVehSeen="7" meanSpeed="12.51" meanTimeLoss="1.04" meanOccupancy="0.36" maxOccupancy="2.74" meanMaxJamLengthInVehicles="0.00" meanMaxJamLengthInMeters="0.00" maxJamLengthInVehicles="0" maxJamLengthInMeters="0.00" jamLengthInVehiclesSum="0" jamLengthInMetersSum="0.00" meanHaltingDuration="0.00" maxHaltingDuration="0.00" haltingDurationSum="0.00" meanIntervalHaltingDuration="0.00" maxIntervalHaltingDuration="0.00" intervalHaltingDurationSum="0.00" startedHalts="0.00" meanVehicleNumber="0.27" maxVehicleNumber="2" />
   <interval begin="0.00" end="300.00" id="xingminlu_north_entry0" sampledSeconds="0.00" nVehEntered="0" nVehLeft="0" nVehSeen="0" meanSpeed="-1.00" meanTimeLoss="-1.00" meanOccupancy="0.00" maxOccupancy="0.00" meanMaxJamLengthInVehicles="0.00" meanMaxJamLengthInMeters="0.00" maxJamLengthInVehicles="0" maxJamLengthInMeters="0.00" jamLengthInVehiclesSum="0" jamLengthInMetersSum="0.00" meanHaltingDuration="0.00" maxHaltingDuration="0.00" haltingDurationSum="0.00" meanIntervalHaltingDuration="0.00" maxIntervalHaltingDuration="0.00" intervalHaltingDurationSum="0.00" startedHalts="0.00" meanVehicleNumber="0.00" maxVehicleNumber="0" />
   <interval begin="0.00" end="300.00" id="xingminlu_north_entry1" sampledSeconds="107.90" nVehEntered="4" nVehLeft="4" nVehSeen="4" meanSpeed="3.37" meanTimeLoss="18.79" meanOccupancy="1.96" maxOccupancy="9.41" meanMaxJamLengthInVehicles="0.21" meanMaxJamLengthInMeters="2.52" maxJamLengthInVehicles="1" maxJamLengthInMeters="12.00" jamLengthInVehiclesSum="63" jamLengthInMetersSum="756.00" meanHaltingDuration="32.50" maxHaltingDuration="64.00" haltingDurationSum="65.00" meanIntervalHaltingDuration="32.50" maxIntervalHaltingDuration="64.00" intervalHaltingDurationSum="65.00" startedHalts="2.00" meanVehicleNumber="0.36" maxVehicleNumber="2" />
   <interval begin="0.00" end="300.00" id="xingminlu_north_entry2" sampledSeconds="251.40" nVehEntered="7" nVehLeft="6" nVehSeen="7" meanSpeed="4.28" meanTimeLoss="23.31" meanOccupancy="2.51" maxOccupancy="6.64" meanMaxJamLengthInVehicles="0.41" meanMaxJamLengthInMeters="2.13" maxJamLengthInVehicles="2" maxJamLengthInMeters="12.50" jamLengthInVehiclesSum="124" jamLengthInMetersSum="640.01" meanHaltingDuration="21.67" maxHaltingDuration="49.00" haltingDurationSum="130.00" meanIntervalHaltingDuration="21.67" maxIntervalHaltingDuration="49.00" intervalHaltingDurationSum="130.00" startedHalts="6.00" meanVehicleNumber="0.85" maxVehicleNumber="2" />
   <interval begin="0.00" end="300.00" id="xingminlu_north_exit0" sampledSeconds="0.00" nVehEntered="0" nVehLeft="0" nVehSeen="0" meanSpeed="-1.00" meanTimeLoss="-1.00" meanOccupancy="0.00" maxOccupancy="0.00" meanMaxJamLengthInVehicles="0.00" meanMaxJamLengthInMeters="0.00" maxJamLengthInVehicles="0" maxJamLengthInMeters="0.00" jamLengthInVehiclesSum="0" jamLengthInMetersSum="0.00" meanHaltingDuration="0.00" maxHaltingDuration="0.00" haltingDurationSum="0.00" meanIntervalHaltingDuration="0.00" maxIntervalHaltingDuration="0.00" intervalHaltingDurationSum="0.00" startedHalts="0.00" meanVehicleNumber="0.00" maxVehicleNumber="0" />
   <interval begin="0.00" end="300.00" id="xingminlu_north_exit1" sampledSeconds="66.86" nVehEntered="4" nVehLeft="4" nVehSeen="4" meanSpeed="11.07" meanTimeLoss="2.06" meanOccupancy="0.60" maxOccupancy="5.53" meanMaxJamLengthInVehicles="0.00" meanMaxJamLengthInMeters="0.00" maxJamLengthInVehicles="0" maxJamLengthInMeters="0.00" jamLengthInVehiclesSum="0" jamLengthInMetersSum="0.00" meanHaltingDuration="0.00" maxHaltingDuration="0.00" haltingDurationSum="0.00" meanIntervalHaltingDuration="0.00" maxIntervalHaltingDuration="0.00" intervalHaltingDurationSum="0.00" startedHalts="0.00" meanVehicleNumber="0.23" maxVehicleNumber="2" />
   <interval begin="0.00" end="300.00" id="xingminlu_north_exit2" sampledSeconds="258.51" nVehEntered="16" nVehLeft="16" nVehSeen="16" meanSpeed="11.45" meanTimeLoss="1.73" meanOccupancy="2.52" maxOccupancy="18.93" meanMaxJamLengthInVehicles="0.00" meanMaxJamLengthInMeters="0.00" maxJamLengthInVehicles="0" maxJamLengthInMeters="0.00" jamLengthInVehiclesSum="0" jamLengthInMetersSum="0.00" meanHaltingDuration="0.00" maxHaltingDuration="0.00" haltingDurationSum="0.00" meanIntervalHaltingDuration="0.00" maxIntervalHaltingDuration="0.00" intervalHaltingDurationSum="0.00" startedHalts="0.00" meanVehicleNumber="0.89" maxVehicleNumber="6" />
   <interval begin="0.00" end="300.00" id="xingminlu_south_entry0" sampledSeconds="0.00" nVehEntered="0" nVehLeft="0" nVehSeen="0" meanSpeed="-1.00" meanTimeLoss="-1.00" meanOccupancy="0.00" maxOccupancy="0.00" meanMaxJamLengthInVehicles="0.00" meanMaxJamLengthInMeters="0.00" maxJamLengthInVehicles="0" maxJamLengthInMeters="0.00" jamLengthInVehiclesSum="0" jamLengthInMetersSum="0.00" meanHaltingDuration="0.00" maxHaltingDuration="0.00" haltingDurationSum="0.00" meanIntervalHaltingDuration="0.00" maxIntervalHaltingDuration="0.00" intervalHaltingDurationSum="0.00" startedHalts="0.00" meanVehicleNumber="0.00" maxVehicleNumber="0" />
   <interval begin="0.00" end="300.00" id="xingminlu_south_entry1" sampledSeconds="0.00" nVehEntered="0" nVehLeft="0" nVehSeen="0" meanSpeed="-1.00" meanTimeLoss="-1.00" meanOccupancy="0.00" maxOccupancy="0.00" meanMaxJamLengthInVehicles="0.00" meanMaxJamLengthInMeters="0.00" maxJamLengthInVehicles="0" maxJamLengthInMeters="0.00" jamLengthInVehiclesSum="0" jamLengthInMetersSum="0.00" meanHaltingDuration="0.00" maxHaltingDuration="0.00" haltingDurationSum="0.00" meanIntervalHaltingDuration="0.00" maxIntervalHaltingDuration="0.00" intervalHaltingDurationSum="0.00" startedHalts="0.00" meanVehicleNumber="0.00" maxVehicleNumber="0" />
   <interval begin="0.00" end="300.00" id="xingminlu_south_entry2" sampledSeconds="1124.38" nVehEntered="12" nVehLeft="5" nVehSeen="12" meanSpeed="1.78" meanTimeLoss="80.97" meanOccupancy="10.76" maxOccupancy="23.01" meanMaxJamLengthInVehicles="3.00" meanMaxJamLengthInMeters="21.63" maxJamLengthInVehicles="8" maxJamLengthInMeters="59.61" jamLengthInVehiclesSum="903" jamLengthInMetersSum="6507.96" meanHaltingDuration="42.05" maxHaltingDuration="93.00" haltingDurationSum="925.00" meanIntervalHaltingDuration="42.05" maxIntervalHaltingDuration="93.00" intervalHaltingDurationSum="925.00" startedHalts="22.00" meanVehicleNumber="3.78" maxVehicleNumber="8" />
   <interval begin="0.00" end="300.00" id="xingminlu_south_exit0" sampledSeconds="0.00" nVehEntered="0" nVehLeft="0" nVehSeen="0" meanSpeed="-1.00" meanTimeLoss="-1.00" meanOccupancy="0.00" maxOccupancy="0.00" meanMaxJamLengthInVehicles="0.00" meanMaxJamLengthInMeters="0.00" maxJamLengthInVehicles="0" maxJamLengthInMeters="0.00" jamLengthInVehiclesSum="0" jamLengthInMetersSum="0.00" meanHaltingDuration="0.00" maxHaltingDuration="0.00" haltingDurationSum="0.00" meanIntervalHaltingDuration="0.00" maxIntervalHaltingDuration="0.00" intervalHaltingDurationSum="0.00" startedHalts="0.00" meanVehicleNumber="0.00" maxVehicleNumber="0" />
   <interval begin="0.00" end="300.00" id="xingminlu_south_exit1" sampledSeconds="150.19" nVehEntered="17" nVehLeft="16" nVehSeen="17" meanSpeed="11.19" meanTimeLoss="1.21" meanOccupancy="1.51" maxOccupancy="8.20" meanMaxJamLengthInVehicles="0.00" meanMaxJamLengthInMeters="0.00" maxJamLengthInVehicles="0" maxJamLengthInMeters="0.00" jamLengthInVehiclesSum="0" jamLengthInMetersSum="0.00" meanHaltingDuration="0.00" maxHaltingDuration="0.00" haltingDurationSum="0.00" meanIntervalHaltingDuration="0.00" maxIntervalHaltingDuration="0.00" intervalHaltingDurationSum="0.00" startedHalts="0.00" meanVehicleNumber="0.53" maxVehicleNumber="3" />
   <interval begin="0.00" end="300.00" id="xingminlu_south_exit2" sampledSeconds="167.26" nVehEntered="15" nVehLeft="14" nVehSeen="15" meanSpeed="11.90" meanTimeLoss="1.16" meanOccupancy="1.51" maxOccupancy="12.08" meanMaxJamLengthInVehicles="0.00" meanMaxJamLengthInMeters="0.00" maxJamLengthInVehicles="0" maxJamLengthInMeters="0.00" jamLengthInVehiclesSum="0" jamLengthInMetersSum="0.00" meanHaltingDuration="0.00" maxHaltingDuration="0.00" haltingDurationSum="0.00" meanIntervalHaltingDuration="0.00" maxIntervalHaltingDuration="0.00" intervalHaltingDurationSum="0.00" startedHalts="0.00" meanVehicleNumber="0.58" maxVehicleNumber="4" />
   <interval begin="0.00" end="300.00" id="fukanglu_north_entry0" sampledSeconds="0.00" nVehEntered="0" nVehLeft="0" nVehSeen="0" meanSpeed="-1.00" meanTimeLoss="-1.00" meanOccupancy="0.00" maxOccupancy="0.00" meanMaxJamLengthInVehicles="0.00" meanMaxJamLengthInMeters="0.00" maxJamLengthInVehicles="0" maxJamLengthInMeters="0.00" jamLengthInVehiclesSum="0" jamLengthInMetersSum="0.00" meanHaltingDuration="0.00" maxHaltingDuration="0.00" haltingDurationSum="0.00" meanIntervalHaltingDuration="0.00" maxIntervalHaltingDuration="0.00" intervalHaltingDurationSum="0.00" startedHalts="0.00" meanVehicleNumber="0.00" maxVehicleNumber="0" />
   <interval begin="0.00" end="300.00" id="fukanglu_north_entry1" sampledSeconds="234.82" nVehEntered="10" nVehLeft="10" nVehSeen="10" meanSpeed="7.79" meanTimeLoss="8.92" meanOccupancy="2.25" maxOccupancy="6.61" meanMaxJamLengthInVehicles="0.13" meanMaxJamLengthInMeters="0.92" maxJamLengthInVehicles="2" maxJamLengthInMeters="14.65" jamLengthInVehiclesSum="40" jamLengthInMetersSum="274.81" meanHaltingDuration="14.33" maxHaltingDuration="32.00" haltingDurationSum="43.00" meanIntervalHaltingDuration="14.33" maxIntervalHaltingDuration="32.00" intervalHaltingDurationSum="43.00" startedHalts="3.00" meanVehicleNumber="0.81" maxVehicleNumber="2" />
   <interval begin="0.00" end="300.00" id="fukanglu_north_entry2" sampledSeconds="206.14" nVehEntered="5" nVehLeft="4" nVehSeen="5" meanSpeed="4.27" meanTimeLoss="28.25" meanOccupancy="1.84" maxOccupancy="5.46" meanMaxJamLengthInVehicles="0.39" meanMaxJamLengthInMeters="1.95" maxJamLengthInVehicles="1" maxJamLengthInMeters="5.00" jamLengthInVehiclesSum="117" jamLengthInMetersSum="585.00" meanHaltingDuration="59.50" maxHaltingDuration="90.00" haltingDurationSum="119.00" meanIntervalHaltingDuration="59.50" maxIntervalHaltingDuration="90.00" intervalHaltingDurationSum="119.00" startedHalts="2.00" meanVehicleNumber="0.69" maxVehicleNumber="2" />
   <interval begin="0.00" end="300.00" id="fukanglu_north_entry3" sampledSeconds="256.24" nVehEntered="5" nVehLeft="5" nVehSeen="5" meanSpeed="3.57" meanTimeLoss="38.62" meanOccupancy="2.28" maxOccupancy="5.46" meanMaxJamLengthInVehicles="0.53" meanMaxJamLengthInMeters="2.75" maxJamLengthInVehicles="2" maxJamLengthInMeters="12.50" jamLengthInVehiclesSum="159" jamLengthInMetersSum="825.01" meanHaltingDuration="32.80" maxHaltingDuration="76.00" haltingDurationSum="164.00" meanIntervalHaltingDuration="32.80" maxIntervalHaltingDuration="76.00" intervalHaltingDurationSum="164.00" startedHalts="5.00" meanVehicleNumber="0.86" maxVehicleNumber="2" />
   <interval begin="0.00" end="300.00" id="fukanglu_north_exit0" sampledSeconds="0.00" nVehEntered="0" nVehLeft="0" nVehSeen="0" meanSpeed="-1.00" meanTimeLoss="-1.00" meanOccupancy="0.00" maxOccupancy="0.00" meanMaxJamLengthInVehicles="0.00" meanMaxJamLengthInMeters="0.00" maxJamLengthInVehicles="0" maxJamLengthInMeters="0.00" jamLengthInVehiclesSum="0" jamLengthInMetersSum="0.00" meanHaltingDuration="0.00" maxHaltingDuration="0.00" haltingDurationSum="0.00" meanIntervalHaltingDuration="0.00" maxIntervalHaltingDuration="0.00" intervalHaltingDurationSum="0.00" startedHalts="0.00" meanVehicleNumber="0.00" maxVehicleNumber="0" />
   <interval begin="0.00" end="300.00" id="fukanglu_north_exit1" sampledSeconds="49.15" nVehEntered="3" nVehLeft="3" nVehSeen="3" meanSpeed="11.48" meanTimeLoss="1.74" meanOccupancy="0.44" maxOccupancy="5.46" meanMaxJamLengthInVehicles="0.00" meanMaxJamLengthInMeters="0.00" maxJamLengthInVehicles="0" maxJamLengthInMeters="0.00" jamLengthInVehiclesSum="0" jamLengthInMetersSum="0.00" meanHaltingDuration="0.00" maxHaltingDuration="0.00" haltingDurationSum="0.00" meanIntervalHaltingDuration="0.00" maxIntervalHaltingDuration="0.00" intervalHaltingDurationSum="0.00" startedHalts="0.00" meanVehicleNumber="0.17" maxVehicleNumber="2" />
   <interval begin="0.00" end="300.00" id="fukanglu_north_exit2" sampledSeconds="118.27" nVehEntered="7" nVehLeft="7" nVehSeen="7" meanSpeed="11.04" meanTimeLoss="2.53" meanOccupancy="1.19" maxOccupancy="12.07" meanMaxJamLengthInVehicles="0.00" meanMaxJamLengthInMeters="0.00" maxJamLengthInVehicles="0" maxJamLengthInMeters="0.00" jamLengthInVehiclesSum="0" jamLengthInMetersSum="0.00" meanHaltingDuration="0.00" maxHaltingDuration="0.00" haltingDurationSum="0.00" meanIntervalHaltingDuration="0.00" maxIntervalHaltingDuration="0.00" intervalHaltingDurationSum="0.00" startedHalts="0.00" meanVehicleNumber="0.41" maxVehicleNumber="4" />
   <interval begin="0.00" end="300.00" id="fukanglu_north_exit3" sampledSeconds="57.50" nVehEntered="4" nVehLeft="4" nVehSeen="4" meanSpeed="12.99" meanTimeLoss="1.54" meanOccupancy="0.51" maxOccupancy="8.19" meanMaxJamLengthInVehicles="0.00" meanMaxJamLengthInMeters="0.00" maxJamLengthInVehicles="0" maxJamLengthInMeters="0.00" jamLengthInVehiclesSum="0" jamLengthInMetersSum="0.00" meanHaltingDuration="0.00" maxHaltingDuration="0.00" haltingDurationSum="0.00" meanIntervalHaltingDuration="0.00" maxIntervalHaltingDuration="0.00" intervalHaltingDurationSum="0.00" startedHalts="0.00" meanVehicleNumber="0.20" maxVehicleNumber="3" />
   <interval begin="0.00" end="300.00" id="fukanglu_south_entry0" sampledSeconds="0.00" nVehEntered="0" nVehLeft="0" nVehSeen="0" meanSpeed="-1.00" meanTimeLoss="-1.00" meanOccupancy="0.00" maxOccupancy="0.00" meanMaxJamLengthInVehicles="0.00" meanMaxJamLengthInMeters="0.00" maxJamLengthInVehicles="0" maxJamLengthInMeters="0.00" jamLengthInVehiclesSum="0" jamLengthInMetersSum="0.00" meanHaltingDuration="0.00" maxHaltingDuration="0.00" haltingDurationSum="0.00" meanIntervalHaltingDuration="0.00" maxIntervalHaltingDuration="0.00" intervalHaltingDurationSum="0.00" startedHalts="0.00" meanVehicleNumber="0.00" maxVehicleNumber="0" />
   <interval begin="0.00" end="300.00" id="fukanglu_south_entry1" sampledSeconds="113.80" nVehEntered="6" nVehLeft="5" nVehSeen="6" meanSpeed="9.55" meanTimeLoss="5.40" meanOccupancy="1.03" maxOccupancy="5.55" meanMaxJamLengthInVehicles="0.06" meanMaxJamLengthInMeters="0.36" maxJamLengthInVehicles="2" maxJamLengthInMeters="12.56" jamLengthInVehiclesSum="18" jamLengthInMetersSum="107.60" meanHaltingDuration="10.00" maxHaltingDuration="10.00" haltingDurationSum="20.00" meanIntervalHaltingDuration="10.00" maxIntervalHaltingDuration="10.00" intervalHaltingDurationSum="20.00" startedHalts="2.00" meanVehicleNumber="0.40" maxVehicleNumber="2" />
   <interval begin="0.00" end="300.00" id="fukanglu_south_entry2" sampledSeconds="364.80" nVehEntered="9" nVehLeft="7" nVehSeen="9" meanSpeed="4.28" meanTimeLoss="27.41" meanOccupancy="3.83" maxOccupancy="12.26" meanMaxJamLengthInVehicles="0.73" meanMaxJamLengthInMeters="5.30" maxJamLengthInVehicles="4" maxJamLengthInMeters="29.61" jamLengthInVehiclesSum="218" jamLengthInMetersSum="1589.66" meanHaltingDuration="55.50" maxHaltingDuration="90.00" haltingDurationSum="222.00" meanIntervalHaltingDuration="55.50" maxIntervalHaltingDuration="90.00" intervalHaltingDurationSum="222.00" startedHalts="4.00" meanVehicleNumber="1.24" maxVehicleNumber="4" />
   <interval begin="0.00" end="300.00" id="fukanglu_south_entry3" sampledSeconds="125.90" nVehEntered="5" nVehLeft="5" nVehSeen="5" meanSpeed="5.99" meanTimeLoss="13.64" meanOccupancy="1.14" maxOccupancy="8.32" meanMaxJamLengthInVehicles="0.18" meanMaxJamLengthInMeters="1.11" maxJamLengthInVehicles="2" maxJamLengthInMeters="12.50" jamLengthInVehiclesSum="55" jamLengthInMetersSum="332.53" meanHaltingDuration="28.50" maxHaltingDuration="32.00" haltingDurationSum="57.00" meanIntervalHaltingDuration="28.50" maxIntervalHaltingDuration="32.00" intervalHaltingDurationSum="57.00" startedHalts="2.00" meanVehicleNumber="0.44" maxVehicleNumber="3" />
   <interval begin="0.00" end="300.00" id="fukanglu_south_exit0" sampledSeconds="0.00" nVehEntered="0" nVehLeft="0" nVehSeen="0" meanSpeed="-1.00" meanTimeLoss="-1.00" meanOccupancy="0.00" maxOccupancy="0.00" meanMaxJamLengthInVehicles="0.00" meanMaxJamLengthInMeters="0.00" maxJamLengthInVehicles="0" maxJamLengthInMeters="0.00" jamLengthInVehiclesSum="0" jamLengthInMetersSum="0.00" meanHaltingDuration="0.00" maxHaltingDuration="0.00" haltingDurationSum="0.00" meanIntervalHaltingDuration="0.00" maxIntervalHaltingDuration="0.00" intervalHaltingDurationSum="0.00" startedHalts="0.00" meanVehicleNumber="0.00" maxVehicleNumber="0" />
   <interval begin="0.00" end="300.00" id="fukanglu_south_exit1" sampledSeconds="31.92" nVehEntered="4" nVehLeft="4" nVehSeen="4" meanSpeed="12.45" meanTimeLoss="0.68" meanOccupancy="0.28" maxOccupancy="2.77" meanMaxJamLengthInVehicles="0.00" meanMaxJamLengthInMeters="0.00" maxJamLengthInVehicles="0" maxJamLengthInMeters="0.00" jamLengthInVehiclesSum="0" jamLengthInMetersSum="0.00" meanHaltingDuration="0.00" maxHaltingDuration="0.00" haltingDurationSum="0.00" meanIntervalHaltingDuration="0.00" maxIntervalHaltingDuration="0.00" intervalHaltingDurationSum="0.00" startedHalts="0.00" meanVehicleNumber="0.11" maxVehicleNumber="1" />
   <interval begin="0.00" end="300.00" id="fukanglu_south_exit2" sampledSeconds="50.31" nVehEntered="7" nVehLeft="7" nVehSeen="7" meanSpeed="12.08" meanTimeLoss="0.62" meanOccupancy="0.46" maxOccupancy="5.55" meanMaxJamLengthInVehicles="0.00" meanMaxJamLengthInMeters="0.00" maxJamLengthInVehicles="0" maxJamLengthInMeters="0.00" jamLengthInVehiclesSum="0" jamLengthInMetersSum="0.00" meanHaltingDuration="0.00" maxHaltingDuration="0.00" haltingDurationSum="0.00" meanIntervalHaltingDuration="0.00" maxIntervalHaltingDuration="0.00" intervalHaltingDurationSum="0.00" startedHalts="0.00" meanVehicleNumber="0.17" maxVehicleNumber="2" />
   <interval begin="0.00" end="300.00" id="fukanglu_south_exit3" sampledSeconds="69.20" nVehEntered="7" nVehLeft="7" nVehSeen="7" meanSpeed="12.23" meanTimeLoss="0.93" meanOccupancy="0.62" maxOccupancy="11.08" meanMaxJamLengthInVehicles="0.00" meanMaxJamLengthInMeters="0.00" maxJamLengthInVehicles="0" maxJamLengthInMeters="0.00" jamLengthInVehiclesSum="0" jamLengthInMetersSum="0.00" meanHaltingDuration="0.00" maxHaltingDuration="0.00" haltingDurationSum="0.00" meanIntervalHaltingDuration="0.00" maxIntervalHaltingDuration="0.00" intervalHaltingDurationSum="0.00" startedHalts="0.00" meanVehicleNumber="0.24" maxVehicleNumber="4" />
   <interval begin="0.00" end="300.00" id="feitianlu_north_entry0" sampledSeconds="0.00" nVehEntered="0" nVehLeft="0" nVehSeen="0" meanSpeed="-1.00" meanTimeLoss="-1.00" meanOccupancy="0.00" maxOccupancy="0.00" meanMaxJamLengthInVehicles="0.00" meanMaxJamLengthInMeters="0.00" maxJamLengthInVehicles="0" maxJamLengthInMeters="0.00" jamLengthInVehiclesSum="0" jamLengthInMetersSum="0.00" meanHaltingDuration="0.00" maxHaltingDuration="0.00" haltingDurationSum="0.00" meanIntervalHaltingDuration="0.00" maxIntervalHaltingDuration="0.00" intervalHaltingDurationSum="0.00" startedHalts="0.00" meanVehicleNumber="0.00" maxVehicleNumber="0" />
   <interval begin="0.00" end="300.00" id="feitianlu_north_entry1" sampledSeconds="113.61" nVehEntered="6" nVehLeft="6" nVehSeen="6" meanSpeed="9.81" meanTimeLoss="4.59" meanOccupancy="0.97" maxOccupancy="2.86" meanMaxJamLengthInVehicles="0.00" meanMaxJamLengthInMeters="0.02" maxJamLengthInVehicles="1" maxJamLengthInMeters="5.00" jamLengthInVehiclesSum="1" jamLengthInMetersSum="5.00" meanHaltingDuration="1.50" maxHaltingDuration="2.00" haltingDurationSum="3.00" meanIntervalHaltingDuration="1.50" maxIntervalHaltingDuration="2.00" intervalHaltingDurationSum="3.00" startedHalts="2.00" meanVehicleNumber="0.39" maxVehicleNumber="2" />
   <interval begin="0.00" end="300.00" id="feitianlu_north_entry2" sampledSeconds="420.39" nVehEntered="9" nVehLeft="8" nVehSeen="9" meanSpeed="3.96" meanTimeLoss="32.06" meanOccupancy="4.16" maxOccupancy="11.89" meanMaxJamLengthInVehicles="0.78" meanMaxJamLengthInMeters="5.29" maxJamLengthInVehicles="4" maxJamLengthInMeters="29.60" jamLengthInVehiclesSum="233" jamLengthInMetersSum="1586.59" meanHaltingDuration="30.12" maxHaltingDuration="97.00" haltingDurationSum="241.00" meanIntervalHaltingDuration="30.12" maxIntervalHaltingDuration="97.00" intervalHaltingDurationSum="241.00" startedHalts="8.00" meanVehicleNumber="1.41" maxVehicleNumber="4" />
   <interval begin="0.00" end="300.00" id="feitianlu_north_exit0" sampledSeconds="0.00" nVehEntered="0" nVehLeft="0" nVehSeen="0" meanSpeed="-1.00" meanTimeLoss="-1.00" meanOccupancy="0.00" maxOccupancy="0.00" meanMaxJamLengthInVehicles="0.00" meanMaxJamLengthInMeters="0.00" maxJamLengthInVehicles="0" maxJamLengthInMeters="0.00" jamLengthInVehiclesSum="0" jamLengthInMetersSum="0.00" meanHaltingDuration="0.00" maxHaltingDuration="0.00" haltingDurationSum="0.00" meanIntervalHaltingDuration="0.00" maxIntervalHaltingDuration="0.00" intervalHaltingDurationSum="0.00" startedHalts="0.00" meanVehicleNumber="0.00" maxVehicleNumber="0" />
   <interval begin="0.00" end="300.00" id="feitianlu_north_exit1" sampledSeconds="195.80" nVehEntered="13" nVehLeft="12" nVehSeen="13" meanSpeed="11.41" meanTimeLoss="2.14" meanOccupancy="1.71" maxOccupancy="16.14" meanMaxJamLengthInVehicles="0.00" meanMaxJamLengthInMeters="0.00" maxJamLengthInVehicles="0" maxJamLengthInMeters="0.00" jamLengthInVehiclesSum="0" jamLengthInMetersSum="0.00" meanHaltingDuration="0.00" maxHaltingDuration="0.00" haltingDurationSum="0.00" meanIntervalHaltingDuration="0.00" maxIntervalHaltingDuration="0.00" intervalHaltingDurationSum="0.00" startedHalts="0.00" meanVehicleNumber="0.67" maxVehicleNumber="6" />
   <interval begin="0.00" end="300.00" id="feitianlu_north_exit2" sampledSeconds="49.06" nVehEntered="3" nVehLeft="3" nVehSeen="3" meanSpeed="11.10" meanTimeLoss="1.10" meanOccupancy="0.43" maxOccupancy="5.38" meanMaxJamLengthInVehicles="0.00" meanMaxJamLengthInMeters="0.00" maxJamLengthInVehicles="0" maxJamLengthInMeters="0.00" jamLengthInVehiclesSum="0" jamLengthInMetersSum="0.00" meanHaltingDuration="0.00" maxHaltingDuration="0.00" haltingDurationSum="0.00" meanIntervalHaltingDuration="0.00" maxIntervalHaltingDuration="0.00" intervalHaltingDurationSum="0.00" startedHalts="0.00" meanVehicleNumber="0.17" maxVehicleNumber="2" />
   <interval begin="0.00" end="300.00" id="feitianlu_south_entry0" sampledSeconds="0.00" nVehEntered="0" nVehLeft="0" nVehSeen="0" meanSpeed="-1.00" meanTimeLoss="-1.00" meanOccupancy="0.00" maxOccupancy="0.00" meanMaxJamLengthInVehicles="0.00" meanMaxJamLengthInMeters="0.00" maxJamLengthInVehicles="0" maxJamLengthInMeters="0.00" jamLengthInVehiclesSum="0" jamLengthInMetersSum="0.00" meanHaltingDuration="0.00" maxHaltingDuration="0.00" haltingDurationSum="0.00" meanIntervalHaltingDuration="0.00" maxIntervalHaltingDuration="0.00" intervalHaltingDurationSum="0.00" startedHalts="0.00" meanVehicleNumber="0.00" maxVehicleNumber="0" />
   <interval begin="0.00" end="300.00" id="feitianlu_south_entry1" sampledSeconds="173.54" nVehEntered="7" nVehLeft="6" nVehSeen="7" meanSpeed="6.74" meanTimeLoss="11.29" meanOccupancy="2.52" maxOccupancy="8.18" meanMaxJamLengthInVehicles="0.21" meanMaxJamLengthInMeters="2.52" maxJamLengthInVehicles="1" maxJamLengthInMeters="12.00" jamLengthInVehiclesSum="63" jamLengthInMetersSum="756.00" meanHaltingDuration="32.50" maxHaltingDuration="63.00" haltingDurationSum="65.00" meanIntervalHaltingDuration="32.50" maxIntervalHaltingDuration="63.00" intervalHaltingDurationSum="65.00" startedHalts="2.00" meanVehicleNumber="0.60" maxVehicleNumber="3" />
   <interval begin="0.00" end="300.00" id="feitianlu_south_entry2" sampledSeconds="287.18" nVehEntered="7" nVehLeft="7" nVehSeen="7" meanSpeed="4.41" meanTimeLoss="26.53" meanOccupancy="2.86" maxOccupancy="13.63" meanMaxJamLengthInVehicles="0.51" meanMaxJamLengthInMeters="3.21" maxJamLengthInVehicles="5" maxJamLengthInMeters="35.05" jamLengthInVehiclesSum="154" jamLengthInMetersSum="962.45" meanHaltingDuration="26.67" maxHaltingDuration="85.00" haltingDurationSum="160.00" meanIntervalHaltingDuration="26.67" maxIntervalHaltingDuration="85.00" intervalHaltingDurationSum="160.00" startedHalts="6.00" meanVehicleNumber="0.98" maxVehicleNumber="5" />
   <interval begin="0.00" end="300.00" id="feitianlu_south_exit0" sampledSeconds="0.00" nVehEntered="0" nVehLeft="0" nVehSeen="0" meanSpeed="-1.00" meanTimeLoss="-1.00" meanOccupancy="0.00" maxOccupancy="0.00" meanMaxJamLengthInVehicles="0.00" meanMaxJamLengthInMeters="0.00" maxJamLengthInVehicles="0" maxJamLengthInMeters="0.00" jamLengthInVehiclesSum="0" jamLengthInMetersSum="0.00" meanHaltingDuration="0.00" maxHaltingDuration="0.00" haltingDurationSum="0.00" meanIntervalHaltingDuration="0.00" maxIntervalHaltingDuration="0.00" intervalHaltingDurationSum="0.00" startedHalts="0.00" meanVehicleNumber="0.00" maxVehicleNumber="0" />
   <interval begin="0.00" end="300.00" id="feitianlu_south_exit1" sampledSeconds="35.26" nVehEntered="4" nVehLeft="3" nVehSeen="4" meanSpeed="9.99" meanTimeLoss="0.60" meanOccupancy="0.50" maxOccupancy="6.54" meanMaxJamLengthInVehicles="0.00" meanMaxJamLengthInMeters="0.00" maxJamLengthInVehicles="0" maxJamLengthInMeters="0.00" jamLengthInVehiclesSum="0" jamLengthInMetersSum="0.00" meanHaltingDuration="0.00" maxHaltingDuration="0.00" haltingDurationSum="0.00" meanIntervalHaltingDuration="0.00" maxIntervalHaltingDuration="0.00" intervalHaltingDurationSum="0.00" startedHalts="0.00" meanVehicleNumber="0.12" maxVehicleNumber="1" />
   <interval begin="0.00" end="300.00" id="feitianlu_south_exit2" sampledSeconds="41.85" nVehEntered="5" nVehLeft="4" nVehSeen="5" meanSpeed="12.42" meanTimeLoss="0.53" meanOccupancy="0.38" maxOccupancy="2.73" meanMaxJamLengthInVehicles="0.00" meanMaxJamLengthInMeters="0.00" maxJamLengthInVehicles="0" maxJamLengthInMeters="0.00" jamLengthInVehiclesSum="0" jamLengthInMetersSum="0.00" meanHaltingDuration="0.00" maxHaltingDuration="0.00" haltingDurationSum="0.00" meanIntervalHaltingDuration="0.00" maxIntervalHaltingDuration="0.00" intervalHaltingDurationSum="0.00" startedHalts="0.00" meanVehicleNumber="0.15" maxVehicleNumber="1" />
   <interval begin="0.00" end="300.00" id="yuanlinlu_second_west_entry0" sampledSeconds="0.00" nVehEntered="0" nVehLeft="0" nVehSeen="0" meanSpeed="-1.00" meanTimeLoss="-1.00" meanOccupancy="0.00" maxOccupancy="0.00" meanMaxJamLengthInVehicles="0.00" meanMaxJamLengthInMeters="0.00" maxJamLengthInVehicles="0" maxJamLengthInMeters="0.00" jamLengthInVehiclesSum="0" jamLengthInMetersSum="0.00" meanHaltingDuration="0.00" maxHaltingDuration="0.00" haltingDurationSum="0.00" meanIntervalHaltingDuration="0.00" maxIntervalHaltingDuration="0.00" intervalHaltingDurationSum="0.00" startedHalts="0.00" meanVehicleNumber="0.00" maxVehicleNumber="0" />
   <interval begin="0.00" end="300.00" id="yuanlinlu_second_west_entry1" sampledSeconds="580.06" nVehEntered="19" nVehLeft="15" nVehSeen="19" meanSpeed="10.56" meanTimeLoss="6.26" meanOccupancy="2.47" maxOccupancy="5.22" meanMaxJamLengthInVehicles="0.09" meanMaxJamLengthInMeters="0.47" maxJamLengthInVehicles="2" maxJamLengthInMeters="12.59" jamLengthInVehiclesSum="27" jamLengthInMetersSum="140.13" meanHaltingDuration="7.75" maxHaltingDuration="24.00" haltingDurationSum="31.00" meanIntervalHaltingDuration="7.75" maxIntervalHaltingDuration="24.00" intervalHaltingDurationSum="31.00" startedHalts="5.00" meanVehicleNumber="1.96" maxVehicleNumber="4" />
   <interval begin="0.00" end="300.00" id="yuanlinlu_second_west_entry2" sampledSeconds="6884.77" nVehEntered="75" nVehLeft="32" nVehSeen="75" meanSpeed="2.78" meanTimeLoss="73.06" meanOccupancy="30.77" maxOccupancy="57.79" meanMaxJamLengthInVehicles="14.36" meanMaxJamLengthInMeters="107.86" maxJamLengthInVehicles="38" maxJamLengthInMeters="286.81" jamLengthInVehiclesSum="4543" jamLengthInMetersSum="34058.28" meanHaltingDuration="33.59" maxHaltingDuration="98.00" haltingDurationSum="4534.00" meanIntervalHaltingDuration="33.59" maxIntervalHaltingDuration="98.00" intervalHaltingDurationSum="4534.00" startedHalts="140.00" meanVehicleNumber="22.99" maxVehicleNumber="43" />
   <interval begin="0.00" end="300.00" id="yuanlinlu_second_west_entry3" sampledSeconds="696.72" nVehEntered="12" nVehLeft="8" nVehSeen="12" meanSpeed="5.89" meanTimeLoss="33.11" meanOccupancy="3.10" maxOccupancy="7.83" meanMaxJamLengthInVehicles="1.03" meanMaxJamLengthInMeters="6.53" maxJamLengthInVehicles="6" maxJamLengthInMeters="42.51" jamLengthInVehiclesSum="308" jamLengthInMetersSum="1957.71" meanHaltingDuration="35.22" maxHaltingDuration="70.00" haltingDurationSum="317.00" meanIntervalHaltingDuration="35.22" maxIntervalHaltingDuration="70.00" intervalHaltingDurationSum="317.00" startedHalts="9.00" meanVehicleNumber="2.34" maxVehicleNumber="6" />
   <interval begin="0.00" end="300.00" id="yuanlinlu_second_west_exit0" sampledSeconds="0.00" nVehEntered="0" nVehLeft="0" nVehSeen="0" meanSpeed="-1.00" meanTimeLoss="-1.00" meanOccupancy="0.00" maxOccupancy="0.00" meanMaxJamLengthInVehicles="0.00" meanMaxJamLengthInMeters="0.00" maxJamLengthInVehicles="0" maxJamLengthInMeters="0.00" jamLengthInVehiclesSum="0" jamLengthInMetersSum="0.00" meanHaltingDuration="0.00" maxHaltingDuration="0.00" haltingDurationSum="0.00" meanIntervalHaltingDuration="0.00" maxIntervalHaltingDuration="0.00" intervalHaltingDurationSum="0.00" startedHalts="0.00" meanVehicleNumber="0.00" maxVehicleNumber="0" />
   <interval begin="0.00" end="300.00" id="yuanlinlu_second_west_exit1" sampledSeconds="170.54" nVehEntered="6" nVehLeft="5" nVehSeen="6" meanSpeed="11.27" meanTimeLoss="2.08" meanOccupancy="0.93" maxOccupancy="4.47" meanMaxJamLengthInVehicles="0.00" meanMaxJamLengthInMeters="0.00" maxJamLengthInVehicles="0" maxJamLengthInMeters="0.00" jamLengthInVehiclesSum="0" jamLengthInMetersSum="0.00" meanHaltingDuration="0.00" maxHaltingDuration="0.00" haltingDurationSum="0.00" meanIntervalHaltingDuration="0.00" maxIntervalHaltingDuration="0.00" intervalHaltingDurationSum="0.00" startedHalts="0.00" meanVehicleNumber="0.57" maxVehicleNumber="3" />
   <interval begin="0.00" end="300.00" id="yuanlinlu_second_west_exit2" sampledSeconds="33.52" nVehEntered="6" nVehLeft="3" nVehSeen="6" meanSpeed="11.90" meanTimeLoss="0.31" meanOccupancy="0.18" maxOccupancy="3.92" meanMaxJamLengthInVehicles="0.00" meanMaxJamLengthInMeters="0.00" maxJamLengthInVehicles="0" maxJamLengthInMeters="0.00" jamLengthInVehiclesSum="0" jamLengthInMetersSum="0.00" meanHaltingDuration="0.00" maxHaltingDuration="0.00" haltingDurationSum="0.00" meanIntervalHaltingDuration="0.00" maxIntervalHaltingDuration="0.00" intervalHaltingDurationSum="0.00" startedHalts="0.00" meanVehicleNumber="0.12" maxVehicleNumber="3" />
   <interval begin="0.00" end="300.00" id="yuanlinlu_second_west_exit3" sampledSeconds="48.78" nVehEntered="3" nVehLeft="3" nVehSeen="3" meanSpeed="12.91" meanTimeLoss="1.26" meanOccupancy="0.23" maxOccupancy="3.16" meanMaxJamLengthInVehicles="0.00" meanMaxJamLengthInMeters="0.00" maxJamLengthInVehicles="0" maxJamLengthInMeters="0.00" jamLengthInVehiclesSum="0" jamLengthInMetersSum="0.00" meanHaltingDuration="0.00" maxHaltingDuration="0.00" haltingDurationSum="0.00" meanIntervalHaltingDuration="0.00" maxIntervalHaltingDuration="0.00" intervalHaltingDurationSum="0.00" startedHalts="0.00" meanVehicleNumber="0.17" maxVehicleNumber="2" />
   <interval begin="0.00" end="300.00" id="yuanlinlu_second_east_entry0" sampledSeconds="0.00" nVehEntered="0" nVehLeft="0" nVehSeen="0" meanSpeed="-1.00" meanTimeLoss="-1.00" meanOccupancy="0.00" maxOccupancy="0.00" meanMaxJamLengthInVehicles="0.00" meanMaxJamLengthInMeters="0.00" maxJamLengthInVehicles="0" maxJamLengthInMeters="0.00" jamLengthInVehiclesSum="0" jamLengthInMetersSum="0.00" meanHaltingDuration="0.00" maxHaltingDuration="0.00" haltingDurationSum="0.00" meanIntervalHaltingDuration="0.00" maxIntervalHaltingDuration="0.00" intervalHaltingDurationSum="0.00" startedHalts="0.00" meanVehicleNumber="0.00" maxVehicleNumber="0" />
   <interval begin="0.00" end="300.00" id="yuanlinlu_second_east_entry1" sampledSeconds="625.87" nVehEntered="15" nVehLeft="11" nVehSeen="15" meanSpeed="5.27" meanTimeLoss="24.73" meanOccupancy="2.70" maxOccupancy="9.15" meanMaxJamLengthInVehicles="1.01" meanMaxJamLengthInMeters="5.99" maxJamLengthInVehicles="3" maxJamLengthInMeters="21.64" jamLengthInVehiclesSum="302" jamLengthInMetersSum="1795.57" meanHaltingDuration="38.75" maxHaltingDuration="99.00" haltingDurationSum="310.00" meanIntervalHaltingDuration="38.75" maxIntervalHaltingDuration="99.00" intervalHaltingDurationSum="310.00" startedHalts="8.00" meanVehicleNumber="2.10" maxVehicleNumber="7" />
   <interval begin="0.00" end="300.00" id="yuanlinlu_second_east_entry2" sampledSeconds="6076.98" nVehEntered="62" nVehLeft="34" nVehSeen="62" meanSpeed="2.49" meanTimeLoss="79.82" meanOccupancy="27.28" maxOccupancy="51.13" meanMaxJamLengthInVehicles="14.57" meanMaxJamLengthInMeters="109.65" maxJamLengthInVehicles="34" maxJamLengthInMeters="257.96" jamLengthInVehiclesSum="4393" jamLengthInMetersSum="33042.08" meanHaltingDuration="62.34" maxHaltingDuration="108.00" haltingDurationSum="4239.00" meanIntervalHaltingDuration="62.34" maxIntervalHaltingDuration="108.00" intervalHaltingDurationSum="4239.00" startedHalts="73.00" meanVehicleNumber="20.29" maxVehicleNumber="38" />
   <interval begin="0.00" end="300.00" id="yuanlinlu_second_east_entry3" sampledSeconds="521.44" nVehEntered="8" nVehLeft="5" nVehSeen="8" meanSpeed="4.46" meanTimeLoss="43.01" meanOccupancy="2.25" maxOccupancy="6.53" meanMaxJamLengthInVehicles="0.96" meanMaxJamLengthInMeters="6.04" maxJamLengthInVehicles="5" maxJamLengthInMeters="35.01" jamLengthInVehiclesSum="288" jamLengthInMetersSum="1812.20" meanHaltingDuration="49.00" maxHaltingDuration="76.00" haltingDurationSum="294.00" meanIntervalHaltingDuration="49.00" maxIntervalHaltingDuration="76.00" intervalHaltingDurationSum="294.00" startedHalts="6.00" meanVehicleNumber="1.74" maxVehicleNumber="5" />
   <interval begin="0.00" end="300.00" id="yuanlinlu_second_east_exit0" sampledSeconds="0.00" nVehEntered="0" nVehLeft="0" nVehSeen="0" meanSpeed="-1.00" meanTimeLoss="-1.00" meanOccupancy="0.00" maxOccupancy="0.00" meanMaxJamLengthInVehicles="0.00" meanMaxJamLengthInMeters="0.00" maxJamLengthInVehicles="0" maxJamLengthInMeters="0.00" jamLengthInVehiclesSum="0" jamLengthInMetersSum="0.00" meanHaltingDuration="0.00" maxHaltingDuration="0.00" haltingDurationSum="0.00" meanIntervalHaltingDuration="0.00" maxIntervalHaltingDuration="0.00" intervalHaltingDurationSum="0.00" startedHalts="0.00" meanVehicleNumber="0.00" maxVehicleNumber="0" />
   <interval begin="0.00" end="300.00" id="yuanlinlu_second_east_exit1" sampledSeconds="187.20" nVehEntered="8" nVehLeft="5" nVehSeen="8" meanSpeed="11.68" meanTimeLoss="1.79" meanOccupancy="0.88" maxOccupancy="3.92" meanMaxJamLengthInVehicles="0.00" meanMaxJamLengthInMeters="0.00" maxJamLengthInVehicles="0" maxJamLengthInMeters="0.00" jamLengthInVehiclesSum="0" jamLengthInMetersSum="0.00" meanHaltingDuration="0.00" maxHaltingDuration="0.00" haltingDurationSum="0.00" meanIntervalHaltingDuration="0.00" maxIntervalHaltingDuration="0.00" intervalHaltingDurationSum="0.00" startedHalts="0.00" meanVehicleNumber="0.63" maxVehicleNumber="3" />
   <interval begin="0.00" end="300.00" id="yuanlinlu_second_east_exit2" sampledSeconds="130.02" nVehEntered="12" nVehLeft="3" nVehSeen="12" meanSpeed="12.36" meanTimeLoss="1.16" meanOccupancy="0.59" maxOccupancy="12.31" meanMaxJamLengthInVehicles="0.00" meanMaxJamLengthInMeters="0.00" maxJamLengthInVehicles="0" maxJamLengthInMeters="0.00" jamLengthInVehiclesSum="0" jamLengthInMetersSum="0.00" meanHaltingDuration="0.00" maxHaltingDuration="0.00" haltingDurationSum="0.00" meanIntervalHaltingDuration="0.00" maxIntervalHaltingDuration="0.00" intervalHaltingDurationSum="0.00" startedHalts="0.00" meanVehicleNumber="0.45" maxVehicleNumber="9" />
   <interval begin="0.00" end="300.00" id="yuanlinlu_second_east_exit3" sampledSeconds="17.86" nVehEntered="2" nVehLeft="1" nVehSeen="2" meanSpeed="11.74" meanTimeLoss="0.80" meanOccupancy="0.08" maxOccupancy="1.31" meanMaxJamLengthInVehicles="0.00" meanMaxJamLengthInMeters="0.00" maxJamLengthInVehicles="0" maxJamLengthInMeters="0.00" jamLengthInVehiclesSum="0" jamLengthInMetersSum="0.00" meanHaltingDuration="0.00" maxHaltingDuration="0.00" haltingDurationSum="0.00" meanIntervalHaltingDuration="0.00" maxIntervalHaltingDuration="0.00" intervalHaltingDurationSum="0.00" startedHalts="0.00" meanVehicleNumber="0.06" maxVehicleNumber="1" />
   <interval begin="0.00" end="300.00" id="yuanlinlu_second_west_mid_entry0" sampledSeconds="0.00" nVehEntered="0" nVehLeft="0" nVehSeen="0" meanSpeed="-1.00" meanTimeLoss="-1.00" meanOccupancy="0.00" maxOccupancy="0.00" meanMaxJamLengthInVehicles="0.00" meanMaxJamLengthInMeters="0.00" maxJamLengthInVehicles="0" maxJamLengthInMeters="0.00" jamLengthInVehiclesSum="0" jamLengthInMetersSum="0.00" meanHaltingDuration="0.00" maxHaltingDuration="0.00" haltingDurationSum="0.00" meanIntervalHaltingDuration="0.00" maxIntervalHaltingDuration="0.00" intervalHaltingDurationSum="0.00" startedHalts="0.00" meanVehicleNumber="0.00" maxVehicleNumber="0" />
   <interval begin="0.00" end="300.00" id="yuanlinlu_second_west_mid_entry1" sampledSeconds="126.56" nVehEntered="8" nVehLeft="8" nVehSeen="8" meanSpeed="9.86" meanTimeLoss="4.96" meanOccupancy="0.57" maxOccupancy="2.74" meanMaxJamLengthInVehicles="0.07" meanMaxJamLengthInMeters="0.37" maxJamLengthInVehicles="1" maxJamLengthInMeters="5.00" jamLengthInVehiclesSum="22" jamLengthInMetersSum="110.00" meanHaltingDuration="12.00" maxHaltingDuration="22.00" haltingDurationSum="24.00" meanIntervalHaltingDuration="12.00" maxIntervalHaltingDuration="22.00" intervalHaltingDurationSum="24.00" startedHalts="2.00" meanVehicleNumber="0.43" maxVehicleNumber="2" />
   <interval begin="0.00" end="300.00" id="yuanlinlu_second_west_mid_entry2" sampledSeconds="994.45" nVehEntered="33" nVehLeft="30" nVehSeen="33" meanSpeed="8.36" meanTimeLoss="11.35" meanOccupancy="4.89" maxOccupancy="21.72" meanMaxJamLengthInVehicles="0.79" meanMaxJamLengthInMeters="5.38" maxJamLengthInVehicles="3" maxJamLengthInMeters="22.14" jamLengthInVehiclesSum="238" jamLengthInMetersSum="1613.09" meanHaltingDuration="30.75" maxHaltingDuration="58.00" haltingDurationSum="246.00" meanIntervalHaltingDuration="30.75" maxIntervalHaltingDuration="58.00" intervalHaltingDurationSum="246.00" startedHalts="8.00" meanVehicleNumber="3.38" maxVehicleNumber="15" />
   <interval begin="0.00" end="300.00" id="yuanlinlu_second_west_mid_entry3" sampledSeconds="342.02" nVehEntered="9" nVehLeft="9" nVehSeen="9" meanSpeed="6.97" meanTimeLoss="18.29" meanOccupancy="1.54" maxOccupancy="5.49" meanMaxJamLengthInVehicles="0.44" meanMaxJamLengthInMeters="2.56" maxJamLengthInVehicles="3" maxJamLengthInMeters="20.00" jamLengthInVehiclesSum="133" jamLengthInMetersSum="767.54" meanHaltingDuration="34.25" maxHaltingDuration="90.00" haltingDurationSum="137.00" meanIntervalHaltingDuration="34.25" maxIntervalHaltingDuration="90.00" intervalHaltingDurationSum="137.00" startedHalts="4.00" meanVehicleNumber="1.15" maxVehicleNumber="4" />
   <interval begin="0.00" end="300.00" id="yuanlinlu_second_west_mid_exit0" sampledSeconds="0.00" nVehEntered="0" nVehLeft="0" nVehSeen="0" meanSpeed="-1.00" meanTimeLoss="-1.00" meanOccupancy="0.00" maxOccupancy="0.00" meanMaxJamLengthInVehicles="0.00" meanMaxJamLengthInMeters="0.00" maxJamLengthInVehicles="0" maxJamLengthInMeters="0.00" jamLengthInVehiclesSum="0" jamLengthInMetersSum="0.00" meanHaltingDuration="0.00" maxHaltingDuration="0.00" haltingDurationSum="0.00" meanIntervalHaltingDuration="0.00" maxIntervalHaltingDuration="0.00" intervalHaltingDurationSum="0.00" startedHalts="0.00" meanVehicleNumber="0.00" maxVehicleNumber="0" />
   <interval begin="0.00" end="300.00" id="yuanlinlu_second_west_mid_exit1" sampledSeconds="46.65" nVehEntered="3" nVehLeft="3" nVehSeen="3" meanSpeed="10.82" meanTimeLoss="1.42" meanOccupancy="0.21" maxOccupancy="2.74" meanMaxJamLengthInVehicles="0.00" meanMaxJamLengthInMeters="0.00" maxJamLengthInVehicles="0" maxJamLengthInMeters="0.00" jamLengthInVehiclesSum="0" jamLengthInMetersSum="0.00" meanHaltingDuration="0.00" maxHaltingDuration="0.00" haltingDurationSum="0.00" meanIntervalHaltingDuration="0.00" maxIntervalHaltingDuration="0.00" intervalHaltingDurationSum="0.00" startedHalts="0.00" meanVehicleNumber="0.16" maxVehicleNumber="2" />
   <interval begin="0.00" end="300.00" id="yuanlinlu_second_west_mid_exit2" sampledSeconds="570.44" nVehEntered="11" nVehLeft="8" nVehSeen="11" meanSpeed="4.55" meanTimeLoss="33.67" meanOccupancy="2.78" maxOccupancy="9.29" meanMaxJamLengthInVehicles="1.05" meanMaxJamLengthInMeters="7.30" maxJamLengthInVehicles="6" maxJamLengthInMeters="42.51" jamLengthInVehiclesSum="314" jamLengthInMetersSum="2189.14" meanHaltingDuration="45.86" maxHaltingDuration="58.00" haltingDurationSum="321.00" meanIntervalHaltingDuration="45.86" maxIntervalHaltingDuration="58.00" intervalHaltingDurationSum="321.00" startedHalts="7.00" meanVehicleNumber="1.92" maxVehicleNumber="7" />
   <interval begin="0.00" end="300.00" id="yuanlinlu_second_west_mid_exit3" sampledSeconds="290.38" nVehEntered="5" nVehLeft="5" nVehSeen="5" meanSpeed="4.49" meanTimeLoss="37.57" meanOccupancy="1.32" maxOccupancy="4.11" meanMaxJamLengthInVehicles="0.56" meanMaxJamLengthInMeters="3.48" maxJamLengthInVehicles="3" maxJamLengthInMeters="20.02" jamLengthInVehiclesSum="167" jamLengthInMetersSum="1044.08" meanHaltingDuration="42.75" maxHaltingDuration="49.00" haltingDurationSum="171.00" meanIntervalHaltingDuration="42.75" maxIntervalHaltingDuration="49.00" intervalHaltingDurationSum="171.00" startedHalts="4.00" meanVehicleNumber="0.98" maxVehicleNumber="3" />
   <interval begin="0.00" end="300.00" id="yuanlinlu_second_east_mid_entry0" sampledSeconds="0.00" nVehEntered="0" nVehLeft="0" nVehSeen="0" meanSpeed="-1.00" meanTimeLoss="-1.00" meanOccupancy="0.00" maxOccupancy="0.00" meanMaxJamLengthInVehicles="0.00" meanMaxJamLengthInMeters="0.00" maxJamLengthInVehicles="0" maxJamLengthInMeters="0.00" jamLengthInVehiclesSum="0" jamLengthInMetersSum="0.00" meanHaltingDuration="0.00" maxHaltingDuration="0.00" haltingDurationSum="0.00" meanIntervalHaltingDuration="0.00" maxIntervalHaltingDuration="0.00" intervalHaltingDurationSum="0.00" startedHalts="0.00" meanVehicleNumber="0.00" maxVehicleNumber="0" />
   <interval begin="0.00" end="300.00" id="yuanlinlu_second_east_mid_entry1" sampledSeconds="99.94" nVehEntered="7" nVehLeft="5" nVehSeen="7" meanSpeed="12.28" meanTimeLoss="1.18" meanOccupancy="0.45" maxOccupancy="2.74" meanMaxJamLengthInVehicles="0.00" meanMaxJamLengthInMeters="0.00" maxJamLengthInVehicles="0" maxJamLengthInMeters="0.00" jamLengthInVehiclesSum="0" jamLengthInMetersSum="0.00" meanHaltingDuration="0.00" maxHaltingDuration="0.00" haltingDurationSum="0.00" meanIntervalHaltingDuration="0.00" maxIntervalHaltingDuration="0.00" intervalHaltingDurationSum="0.00" startedHalts="0.00" meanVehicleNumber="0.34" maxVehicleNumber="2" />
   <interval begin="0.00" end="300.00" id="yuanlinlu_second_east_mid_entry2" sampledSeconds="731.06" nVehEntered="28" nVehLeft="21" nVehSeen="28" meanSpeed="6.08" meanTimeLoss="13.74" meanOccupancy="3.63" maxOccupancy="12.91" meanMaxJamLengthInVehicles="0.97" meanMaxJamLengthInMeters="6.95" maxJamLengthInVehicles="8" maxJamLengthInMeters="59.68" jamLengthInVehiclesSum="290" jamLengthInMetersSum="2085.64" meanHaltingDuration="30.00" maxHaltingDuration="69.00" haltingDurationSum="300.00" meanIntervalHaltingDuration="30.00" maxIntervalHaltingDuration="69.00" intervalHaltingDurationSum="300.00" startedHalts="10.00" meanVehicleNumber="2.49" maxVehicleNumber="9" />
   <interval begin="0.00" end="300.00" id="yuanlinlu_second_east_mid_entry3" sampledSeconds="180.25" nVehEntered="9" nVehLeft="6" nVehSeen="9" meanSpeed="11.06" meanTimeLoss="4.00" meanOccupancy="0.81" maxOccupancy="5.48" meanMaxJamLengthInVehicles="0.06" meanMaxJamLengthInMeters="0.30" maxJamLengthInVehicles="1" maxJamLengthInMeters="5.00" jamLengthInVehiclesSum="18" jamLengthInMetersSum="90.00" meanHaltingDuration="19.00" maxHaltingDuration="19.00" haltingDurationSum="19.00" meanIntervalHaltingDuration="19.00" maxIntervalHaltingDuration="19.00" intervalHaltingDurationSum="19.00" startedHalts="1.00" meanVehicleNumber="0.61" maxVehicleNumber="4" />
   <interval begin="0.00" end="300.00" id="yuanlinlu_second_east_mid_exit0" sampledSeconds="0.00" nVehEntered="0" nVehLeft="0" nVehSeen="0" meanSpeed="-1.00" meanTimeLoss="-1.00" meanOccupancy="0.00" maxOccupancy="0.00" meanMaxJamLengthInVehicles="0.00" meanMaxJamLengthInMeters="0.00" maxJamLengthInVehicles="0" maxJamLengthInMeters="0.00" jamLengthInVehiclesSum="0" jamLengthInMetersSum="0.00" meanHaltingDuration="0.00" maxHaltingDuration="0.00" haltingDurationSum="0.00" meanIntervalHaltingDuration="0.00" maxIntervalHaltingDuration="0.00" intervalHaltingDurationSum="0.00" startedHalts="0.00" meanVehicleNumber="0.00" maxVehicleNumber="0" />
   <interval begin="0.00" end="300.00" id="yuanlinlu_second_east_mid_exit1" sampledSeconds="69.00" nVehEntered="4" nVehLeft="1" nVehSeen="4" meanSpeed="11.55" meanTimeLoss="2.10" meanOccupancy="0.35" maxOccupancy="4.69" meanMaxJamLengthInVehicles="0.01" meanMaxJamLengthInMeters="0.05" maxJamLengthInVehicles="1" maxJamLengthInMeters="5.00" jamLengthInVehiclesSum="3" jamLengthInMetersSum="15.00" meanHaltingDuration="4.00" maxHaltingDuration="4.00" haltingDurationSum="4.00" meanIntervalHaltingDuration="4.00" maxIntervalHaltingDuration="4.00" intervalHaltingDurationSum="4.00" startedHalts="1.00" meanVehicleNumber="0.23" maxVehicleNumber="3" />
   <interval begin="0.00" end="300.00" id="yuanlinlu_second_east_mid_exit2" sampledSeconds="1851.58" nVehEntered="25" nVehLeft="18" nVehSeen="25" meanSpeed="3.40" meanTimeLoss="55.38" meanOccupancy="8.74" maxOccupancy="26.65" meanMaxJamLengthInVehicles="4.03" meanMaxJamLengthInMeters="29.87" maxJamLengthInVehicles="15" maxJamLengthInMeters="112.13" jamLengthInVehiclesSum="1208" jamLengthInMetersSum="8960.14" meanHaltingDuration="68.11" maxHaltingDuration="103.00" haltingDurationSum="1226.00" meanIntervalHaltingDuration="68.11" maxIntervalHaltingDuration="103.00" intervalHaltingDurationSum="1226.00" startedHalts="18.00" meanVehicleNumber="6.22" maxVehicleNumber="19" />
   <interval begin="0.00" end="300.00" id="yuanlinlu_second_east_mid_exit3" sampledSeconds="61.55" nVehEntered="5" nVehLeft="5" nVehSeen="5" meanSpeed="12.73" meanTimeLoss="1.15" meanOccupancy="0.28" maxOccupancy="2.74" meanMaxJamLengthInVehicles="0.00" meanMaxJamLengthInMeters="0.00" maxJamLengthInVehicles="0" maxJamLengthInMeters="0.00" jamLengthInVehiclesSum="0" jamLengthInMetersSum="0.00" meanHaltingDuration="0.00" maxHaltingDuration="0.00" haltingDurationSum="0.00" meanIntervalHaltingDuration="0.00" maxIntervalHaltingDuration="0.00" intervalHaltingDurationSum="0.00" startedHalts="0.00" meanVehicleNumber="0.21" maxVehicleNumber="2" />
   <interval begin="0.00" end="300.00" id="xingminlu_second_north_entry0" sampledSeconds="0.00" nVehEntered="0" nVehLeft="0" nVehSeen="0" meanSpeed="-1.00" meanTimeLoss="-1.00" meanOccupancy="0.00" maxOccupancy="0.00" meanMaxJamLengthInVehicles="0.00" meanMaxJamLengthInMeters="0.00" maxJamLengthInVehicles="0" maxJamLengthInMeters="0.00" jamLengthInVehiclesSum="0" jamLengthInMetersSum="0.00" meanHaltingDuration="0.00" maxHaltingDuration="0.00" haltingDurationSum="0.00" meanIntervalHaltingDuration="0.00" maxIntervalHaltingDuration="0.00" intervalHaltingDurationSum="0.00" startedHalts="0.00" meanVehicleNumber="0.00" maxVehicleNumber="0" />
   <interval begin="0.00" end="300.00" id="xingminlu_second_north_entry1" sampledSeconds="5.69" nVehEntered="1" nVehLeft="1" nVehSeen="1" meanSpeed="10.03" meanTimeLoss="0.71" meanOccupancy="0.06" maxOccupancy="2.77" meanMaxJamLengthInVehicles="0.00" meanMaxJamLengthInMeters="0.00" maxJamLengthInVehicles="0" maxJamLengthInMeters="0.00" jamLengthInVehiclesSum="0" jamLengthInMetersSum="0.00" meanHaltingDuration="0.00" maxHaltingDuration="0.00" haltingDurationSum="0.00" meanIntervalHaltingDuration="0.00" maxIntervalHaltingDuration="0.00" intervalHaltingDurationSum="0.00" startedHalts="0.00" meanVehicleNumber="0.02" maxVehicleNumber="1" />
   <interval begin="0.00" end="300.00" id="xingminlu_second_north_entry2" sampledSeconds="183.09" nVehEntered="12" nVehLeft="12" nVehSeen="12" meanSpeed="11.87" meanTimeLoss="1.42" meanOccupancy="1.70" maxOccupancy="16.60" meanMaxJamLengthInVehicles="0.00" meanMaxJamLengthInMeters="0.00" maxJamLengthInVehicles="0" maxJamLengthInMeters="0.00" jamLengthInVehiclesSum="0" jamLengthInMetersSum="0.00" meanHaltingDuration="0.00" maxHaltingDuration="0.00" haltingDurationSum="0.00" meanIntervalHaltingDuration="0.00" maxIntervalHaltingDuration="0.00" intervalHaltingDurationSum="0.00" startedHalts="0.00" meanVehicleNumber="0.64" maxVehicleNumber="6" />
   <interval begin="0.00" end="300.00" id="xingminlu_second_north_exit0" sampledSeconds="0.00" nVehEntered="0" nVehLeft="0" nVehSeen="0" meanSpeed="-1.00" meanTimeLoss="-1.00" meanOccupancy="0.00" maxOccupancy="0.00" meanMaxJamLengthInVehicles="0.00" meanMaxJamLengthInMeters="0.00" maxJamLengthInVehicles="0" maxJamLengthInMeters="0.00" jamLengthInVehiclesSum="0" jamLengthInMetersSum="0.00" meanHaltingDuration="0.00" maxHaltingDuration="0.00" haltingDurationSum="0.00" meanIntervalHaltingDuration="0.00" maxIntervalHaltingDuration="0.00" intervalHaltingDurationSum="0.00" startedHalts="0.00" meanVehicleNumber="0.00" maxVehicleNumber="0" />
   <interval begin="0.00" end="300.00" id="xingminlu_second_north_exit1" sampledSeconds="92.76" nVehEntered="4" nVehLeft="4" nVehSeen="4" meanSpeed="8.05" meanTimeLoss="7.89" meanOccupancy="1.01" maxOccupancy="3.93" meanMaxJamLengthInVehicles="0.06" meanMaxJamLengthInMeters="0.33" maxJamLengthInVehicles="1" maxJamLengthInMeters="7.10" jamLengthInVehiclesSum="18" jamLengthInMetersSum="100.50" meanHaltingDuration="7.00" maxHaltingDuration="14.00" haltingDurationSum="21.00" meanIntervalHaltingDuration="7.00" maxIntervalHaltingDuration="14.00" intervalHaltingDurationSum="21.00" startedHalts="3.00" meanVehicleNumber="0.32" maxVehicleNumber="1" />
   <interval begin="0.00" end="300.00" id="xingminlu_second_north_exit2" sampledSeconds="1621.78" nVehEntered="14" nVehLeft="4" nVehSeen="14" meanSpeed="1.31" meanTimeLoss="104.33" meanOccupancy="15.39" maxOccupancy="34.37" meanMaxJamLengthInVehicles="4.33" meanMaxJamLengthInMeters="31.35" maxJamLengthInVehicles="11" maxJamLengthInMeters="87.91" jamLengthInVehiclesSum="1334" jamLengthInMetersSum="9629.38" meanHaltingDuration="34.35" maxHaltingDuration="88.00" haltingDurationSum="1374.00" meanIntervalHaltingDuration="34.35" maxIntervalHaltingDuration="88.00" intervalHaltingDurationSum="1374.00" startedHalts="40.00" meanVehicleNumber="5.44" maxVehicleNumber="12" />
   <interval begin="0.00" end="300.00" id="xingminlu_second_south_entry0" sampledSeconds="0.00" nVehEntered="0" nVehLeft="0" nVehSeen="0" meanSpeed="-1.00" meanTimeLoss="-1.00" meanOccupancy="0.00" maxOccupancy="0.00" meanMaxJamLengthInVehicles="0.00" meanMaxJamLengthInMeters="0.00" maxJamLengthInVehicles="0" maxJamLengthInMeters="0.00" jamLengthInVehiclesSum="0" jamLengthInMetersSum="0.00" meanHaltingDuration="0.00" maxHaltingDuration="0.00" haltingDurationSum="0.00" meanIntervalHaltingDuration="0.00" maxIntervalHaltingDuration="0.00" intervalHaltingDurationSum="0.00" startedHalts="0.00" meanVehicleNumber="0.00" maxVehicleNumber="0" />
   <interval begin="0.00" end="300.00" id="xingminlu_second_south_entry1" sampledSeconds="156.47" nVehEntered="5" nVehLeft="4" nVehSeen="5" meanSpeed="5.52" meanTimeLoss="18.86" meanOccupancy="1.39" maxOccupancy="2.73" meanMaxJamLengthInVehicles="0.23" meanMaxJamLengthInMeters="1.13" maxJamLengthInVehicles="1" maxJamLengthInMeters="5.00" jamLengthInVehiclesSum="68" jamLengthInMetersSum="340.00" meanHaltingDuration="35.00" maxHaltingDuration="44.00" haltingDurationSum="70.00" meanIntervalHaltingDuration="35.00" maxIntervalHaltingDuration="44.00" intervalHaltingDurationSum="70.00" startedHalts="2.00" meanVehicleNumber="0.53" maxVehicleNumber="1" />
   <interval begin="0.00" end="300.00" id="xingminlu_second_south_entry2" sampledSeconds="733.78" nVehEntered="10" nVehLeft="6" nVehSeen="10" meanSpeed="2.36" meanTimeLoss="59.71" meanOccupancy="7.20" maxOccupancy="14.80" meanMaxJamLengthInVehicles="1.71" meanMaxJamLengthInMeters="11.75" maxJamLengthInVehicles="4" maxJamLengthInMeters="29.60" jamLengthInVehiclesSum="513" jamLengthInMetersSum="3524.29" meanHaltingDuration="31.18" maxHaltingDuration="81.00" haltingDurationSum="530.00" meanIntervalHaltingDuration="31.18" maxIntervalHaltingDuration="81.00" intervalHaltingDurationSum="530.00" startedHalts="17.00" meanVehicleNumber="2.45" maxVehicleNumber="5" />
   <interval begin="0.00" end="300.00" id="xingminlu_second_south_exit0" sampledSeconds="0.00" nVehEntered="0" nVehLeft="0" nVehSeen="0" meanSpeed="-1.00" meanTimeLoss="-1.00" meanOccupancy="0.00" maxOccupancy="0.00" meanMaxJamLengthInVehicles="0.00" meanMaxJamLengthInMeters="0.00" maxJamLengthInVehicles="0" maxJamLengthInMeters="0.00" jamLengthInVehiclesSum="0" jamLengthInMetersSum="0.00" meanHaltingDuration="0.00" maxHaltingDuration="0.00" haltingDurationSum="0.00" meanIntervalHaltingDuration="0.00" maxIntervalHaltingDuration="0.00" intervalHaltingDurationSum="0.00" startedHalts="0.00" meanVehicleNumber="0.00" maxVehicleNumber="0" />
   <interval begin="0.00" end="300.00" id="xingminlu_second_south_exit1" sampledSeconds="195.22" nVehEntered="13" nVehLeft="13" nVehSeen="13" meanSpeed="12.16" meanTimeLoss="1.52" meanOccupancy="1.78" maxOccupancy="5.59" meanMaxJamLengthInVehicles="0.00" meanMaxJamLengthInMeters="0.00" maxJamLengthInVehicles="0" maxJamLengthInMeters="0.00" jamLengthInVehiclesSum="0" jamLengthInMetersSum="0.00" meanHaltingDuration="0.00" maxHaltingDuration="0.00" haltingDurationSum="0.00" meanIntervalHaltingDuration="0.00" maxIntervalHaltingDuration="0.00" intervalHaltingDurationSum="0.00" startedHalts="0.00" meanVehicleNumber="0.67" maxVehicleNumber="2" />
   <interval begin="0.00" end="300.00" id="xingminlu_second_south_exit2" sampledSeconds="34.09" nVehEntered="4" nVehLeft="2" nVehSeen="4" meanSpeed="12.02" meanTimeLoss="0.81" meanOccupancy="0.31" maxOccupancy="5.03" meanMaxJamLengthInVehicles="0.00" meanMaxJamLengthInMeters="0.00" maxJamLengthInVehicles="0" maxJamLengthInMeters="0.00" jamLengthInVehiclesSum="0" jamLengthInMetersSum="0.00" meanHaltingDuration="0.00" maxHaltingDuration="0.00" haltingDurationSum="0.00" meanIntervalHaltingDuration="0.00" maxIntervalHaltingDuration="0.00" intervalHaltingDurationSum="0.00" startedHalts="0.00" meanVehicleNumber="0.12" maxVehicleNumber="2" />
   <interval begin="0.00" end="300.00" id="fukanglu_second_north_entry0" sampledSeconds="0.00" nVehEntered="0" nVehLeft="0" nVehSeen="0" meanSpeed="-1.00" meanTimeLoss="-1.00" meanOccupancy="0.00" maxOccupancy="0.00" meanMaxJamLengthInVehicles="0.00" meanMaxJamLengthInMeters="0.00" maxJamLengthInVehicles="0" maxJamLengthInMeters="0.00" jamLengthInVehiclesSum="0" jamLengthInMetersSum="0.00" meanHaltingDuration="0.00" maxHaltingDuration="0.00" haltingDurationSum="0.00" meanIntervalHaltingDuration="0.00" maxIntervalHaltingDuration="0.00" intervalHaltingDurationSum="0.00" startedHalts="0.00" meanVehicleNumber="0.00" maxVehicleNumber="0" />
   <interval begin="0.00" end="300.00" id="fukanglu_second_north_entry1" sampledSeconds="61.74" nVehEntered="10" nVehLeft="10" nVehSeen="10" meanSpeed="11.68" meanTimeLoss="0.74" meanOccupancy="0.54" maxOccupancy="6.61" meanMaxJamLengthInVehicles="0.00" meanMaxJamLengthInMeters="0.00" maxJamLengthInVehicles="0" maxJamLengthInMeters="0.00" jamLengthInVehiclesSum="0" jamLengthInMetersSum="0.00" meanHaltingDuration="0.00" maxHaltingDuration="0.00" haltingDurationSum="0.00" meanIntervalHaltingDuration="0.00" maxIntervalHaltingDuration="0.00" intervalHaltingDurationSum="0.00" startedHalts="0.00" meanVehicleNumber="0.22" maxVehicleNumber="2" />
   <interval begin="0.00" end="300.00" id="fukanglu_second_north_entry2" sampledSeconds="149.71" nVehEntered="17" nVehLeft="17" nVehSeen="17" meanSpeed="12.19" meanTimeLoss="0.73" meanOccupancy="1.44" maxOccupancy="12.07" meanMaxJamLengthInVehicles="0.00" meanMaxJamLengthInMeters="0.00" maxJamLengthInVehicles="0" maxJamLengthInMeters="0.00" jamLengthInVehiclesSum="0" jamLengthInMetersSum="0.00" meanHaltingDuration="0.00" maxHaltingDuration="0.00" haltingDurationSum="0.00" meanIntervalHaltingDuration="0.00" maxIntervalHaltingDuration="0.00" intervalHaltingDurationSum="0.00" startedHalts="0.00" meanVehicleNumber="0.52" maxVehicleNumber="4" />
   <interval begin="0.00" end="300.00" id="fukanglu_second_north_entry3" sampledSeconds="86.37" nVehEntered="9" nVehLeft="9" nVehSeen="9" meanSpeed="11.95" meanTimeLoss="1.10" meanOccupancy="0.77" maxOccupancy="10.92" meanMaxJamLengthInVehicles="0.00" meanMaxJamLengthInMeters="0.00" maxJamLengthInVehicles="0" maxJamLengthInMeters="0.00" jamLengthInVehiclesSum="0" jamLengthInMetersSum="0.00" meanHaltingDuration="0.00" maxHaltingDuration="0.00" haltingDurationSum="0.00" meanIntervalHaltingDuration="0.00" maxIntervalHaltingDuration="0.00" intervalHaltingDurationSum="0.00" startedHalts="0.00" meanVehicleNumber="0.30" maxVehicleNumber="4" />
   <interval begin="0.00" end="300.00" id="fukanglu_second_north_exit0" sampledSeconds="0.00" nVehEntered="0" nVehLeft="0" nVehSeen="0" meanSpeed="-1.00" meanTimeLoss="-1.00" meanOccupancy="0.00" maxOccupancy="0.00" meanMaxJamLengthInVehicles="0.00" meanMaxJamLengthInMeters="0.00" maxJamLengthInVehicles="0" maxJamLengthInMeters="0.00" jamLengthInVehiclesSum="0" jamLengthInMetersSum="0.00" meanHaltingDuration="0.00" maxHaltingDuration="0.00" haltingDurationSum="0.00" meanIntervalHaltingDuration="0.00" maxIntervalHaltingDuration="0.00" intervalHaltingDurationSum="0.00" startedHalts="0.00" meanVehicleNumber="0.00" maxVehicleNumber="0" />
   <interval begin="0.00" end="300.00" id="fukanglu_second_north_exit1" sampledSeconds="56.65" nVehEntered="4" nVehLeft="3" nVehSeen="4" meanSpeed="11.72" meanTimeLoss="0.83" meanOccupancy="0.50" maxOccupancy="5.46" meanMaxJamLengthInVehicles="0.00" meanMaxJamLengthInMeters="0.00" maxJamLengthInVehicles="0" maxJamLengthInMeters="0.00" jamLengthInVehiclesSum="0" jamLengthInMetersSum="0.00" meanHaltingDuration="0.00" maxHaltingDuration="0.00" haltingDurationSum="0.00" meanIntervalHaltingDuration="0.00" maxIntervalHaltingDuration="0.00" intervalHaltingDurationSum="0.00" startedHalts="0.00" meanVehicleNumber="0.20" maxVehicleNumber="2" />
   <interval begin="0.00" end="300.00" id="fukanglu_second_north_exit2" sampledSeconds="46.28" nVehEntered="3" nVehLeft="3" nVehSeen="3" meanSpeed="7.54" meanTimeLoss="7.21" meanOccupancy="0.41" maxOccupancy="5.46" meanMaxJamLengthInVehicles="0.04" meanMaxJamLengthInMeters="0.23" maxJamLengthInVehicles="2" maxJamLengthInMeters="12.65" jamLengthInVehiclesSum="12" jamLengthInMetersSum="70.18" meanHaltingDuration="7.00" maxHaltingDuration="7.00" haltingDurationSum="14.00" meanIntervalHaltingDuration="7.00" maxIntervalHaltingDuration="7.00" intervalHaltingDurationSum="14.00" startedHalts="2.00" meanVehicleNumber="0.16" maxVehicleNumber="2" />
   <interval begin="0.00" end="300.00" id="fukanglu_second_north_exit3" sampledSeconds="358.62" nVehEntered="5" nVehLeft="5" nVehSeen="5" meanSpeed="2.18" meanTimeLoss="60.21" meanOccupancy="3.13" maxOccupancy="10.92" meanMaxJamLengthInVehicles="0.90" meanMaxJamLengthInMeters="5.43" maxJamLengthInVehicles="3" maxJamLengthInMeters="20.30" jamLengthInVehiclesSum="270" jamLengthInMetersSum="1629.68" meanHaltingDuration="33.88" maxHaltingDuration="100.00" haltingDurationSum="271.00" meanIntervalHaltingDuration="33.88" maxIntervalHaltingDuration="100.00" intervalHaltingDurationSum="271.00" startedHalts="9.00" meanVehicleNumber="1.21" maxVehicleNumber="4" />
   <interval begin="0.00" end="300.00" id="fukanglu_second_south_entry0" sampledSeconds="0.00" nVehEntered="0" nVehLeft="0" nVehSeen="0" meanSpeed="-1.00" meanTimeLoss="-1.00" meanOccupancy="0.00" maxOccupancy="0.00" meanMaxJamLengthInVehicles="0.00" meanMaxJamLengthInMeters="0.00" maxJamLengthInVehicles="0" maxJamLengthInMeters="0.00" jamLengthInVehiclesSum="0" jamLengthInMetersSum="0.00" meanHaltingDuration="0.00" maxHaltingDuration="0.00" haltingDurationSum="0.00" meanIntervalHaltingDuration="0.00" maxIntervalHaltingDuration="0.00" intervalHaltingDurationSum="0.00" startedHalts="0.00" meanVehicleNumber="0.00" maxVehicleNumber="0" />
   <interval begin="0.00" end="300.00" id="fukanglu_second_south_entry1" sampledSeconds="0.00" nVehEntered="0" nVehLeft="0" nVehSeen="0" meanSpeed="-1.00" meanTimeLoss="-1.00" meanOccupancy="0.00" maxOccupancy="0.00" meanMaxJamLengthInVehicles="0.00" meanMaxJamLengthInMeters="0.00" maxJamLengthInVehicles="0" maxJamLengthInMeters="0.00" jamLengthInVehiclesSum="0" jamLengthInMetersSum="0.00" meanHaltingDuration="0.00" maxHaltingDuration="0.00" haltingDurationSum="0.00" meanIntervalHaltingDuration="0.00" maxIntervalHaltingDuration="0.00" intervalHaltingDurationSum="0.00" startedHalts="0.00" meanVehicleNumber="0.00" maxVehicleNumber="0" />
   <interval begin="0.00" end="300.00" id="fukanglu_second_south_entry2" sampledSeconds="563.97" nVehEntered="12" nVehLeft="9" nVehSeen="12" meanSpeed="3.55" meanTimeLoss="34.59" meanOccupancy="5.46" maxOccupancy="12.26" meanMaxJamLengthInVehicles="1.13" meanMaxJamLengthInMeters="7.20" maxJamLengthInVehicles="4" maxJamLengthInMeters="29.62" jamLengthInVehiclesSum="340" jamLengthInMetersSum="2159.32" meanHaltingDuration="38.78" maxHaltingDuration="81.00" haltingDurationSum="349.00" meanIntervalHaltingDuration="38.78" maxIntervalHaltingDuration="81.00" intervalHaltingDurationSum="349.00" startedHalts="9.00" meanVehicleNumber="1.89" maxVehicleNumber="4" />
   <interval begin="0.00" end="300.00" id="fukanglu_second_south_entry3" sampledSeconds="72.14" nVehEntered="2" nVehLeft="2" nVehSeen="2" meanSpeed="5.00" meanTimeLoss="20.90" meanOccupancy="0.86" maxOccupancy="3.94" meanMaxJamLengthInVehicles="0.11" meanMaxJamLengthInMeters="0.76" maxJamLengthInVehicles="1" maxJamLengthInMeters="7.10" jamLengthInVehiclesSum="32" jamLengthInMetersSum="227.20" meanHaltingDuration="33.00" maxHaltingDuration="33.00" haltingDurationSum="33.00" meanIntervalHaltingDuration="33.00" maxIntervalHaltingDuration="33.00" intervalHaltingDurationSum="33.00" startedHalts="1.00" meanVehicleNumber="0.24" maxVehicleNumber="1" />
   <interval begin="0.00" end="300.00" id="fukanglu_second_south_exit0" sampledSeconds="0.00" nVehEntered="0" nVehLeft="0" nVehSeen="0" meanSpeed="-1.00" meanTimeLoss="-1.00" meanOccupancy="0.00" maxOccupancy="0.00" meanMaxJamLengthInVehicles="0.00" meanMaxJamLengthInMeters="0.00" maxJamLengthInVehicles="0" maxJamLengthInMeters="0.00" jamLengthInVehiclesSum="0" jamLengthInMetersSum="0.00" meanHaltingDuration="0.00" maxHaltingDuration="0.00" haltingDurationSum="0.00" meanIntervalHaltingDuration="0.00" maxIntervalHaltingDuration="0.00" intervalHaltingDurationSum="0.00" startedHalts="0.00" meanVehicleNumber="0.00" maxVehicleNumber="0" />
   <interval begin="0.00" end="300.00" id="fukanglu_second_south_exit1" sampledSeconds="41.33" nVehEntered="3" nVehLeft="3" nVehSeen="3" meanSpeed="13.26" meanTimeLoss="1.51" meanOccupancy="0.38" maxOccupancy="5.59" meanMaxJamLengthInVehicles="0.00" meanMaxJamLengthInMeters="0.00" maxJamLengthInVehicles="0" maxJamLengthInMeters="0.00" jamLengthInVehiclesSum="0" jamLengthInMetersSum="0.00" meanHaltingDuration="0.00" maxHaltingDuration="0.00" haltingDurationSum="0.00" meanIntervalHaltingDuration="0.00" maxIntervalHaltingDuration="0.00" intervalHaltingDurationSum="0.00" startedHalts="0.00" meanVehicleNumber="0.14" maxVehicleNumber="2" />
   <interval begin="0.00" end="300.00" id="fukanglu_second_south_exit2" sampledSeconds="27.13" nVehEntered="2" nVehLeft="2" nVehSeen="2" meanSpeed="13.56" meanTimeLoss="0.57" meanOccupancy="0.24" maxOccupancy="5.59" meanMaxJamLengthInVehicles="0.00" meanMaxJamLengthInMeters="0.00" maxJamLengthInVehicles="0" maxJamLengthInMeters="0.00" jamLengthInVehiclesSum="0" jamLengthInMetersSum="0.00" meanHaltingDuration="0.00" maxHaltingDuration="0.00" haltingDurationSum="0.00" meanIntervalHaltingDuration="0.00" maxIntervalHaltingDuration="0.00" intervalHaltingDurationSum="0.00" startedHalts="0.00" meanVehicleNumber="0.10" maxVehicleNumber="2" />
   <interval begin="0.00" end="300.00" id="fukanglu_second_south_exit3" sampledSeconds="44.70" nVehEntered="4" nVehLeft="3" nVehSeen="4" meanSpeed="12.64" meanTimeLoss="1.26" meanOccupancy="0.41" maxOccupancy="8.38" meanMaxJamLengthInVehicles="0.00" meanMaxJamLengthInMeters="0.00" maxJamLengthInVehicles="0" maxJamLengthInMeters="0.00" jamLengthInVehiclesSum="0" jamLengthInMetersSum="0.00" meanHaltingDuration="0.00" maxHaltingDuration="0.00" haltingDurationSum="0.00" meanIntervalHaltingDuration="0.00" maxIntervalHaltingDuration="0.00" intervalHaltingDurationSum="0.00" startedHalts="0.00" meanVehicleNumber="0.16" maxVehicleNumber="3" />
   <interval begin="0.00" end="300.00" id="feitianlu_second_north_entry0" sampledSeconds="0.00" nVehEntered="0" nVehLeft="0" nVehSeen="0" meanSpeed="-1.00" meanTimeLoss="-1.00" meanOccupancy="0.00" maxOccupancy="0.00" meanMaxJamLengthInVehicles="0.00" meanMaxJamLengthInMeters="0.00" maxJamLengthInVehicles="0" maxJamLengthInMeters="0.00" jamLengthInVehiclesSum="0" jamLengthInMetersSum="0.00" meanHaltingDuration="0.00" maxHaltingDuration="0.00" haltingDurationSum="0.00" meanIntervalHaltingDuration="0.00" maxIntervalHaltingDuration="0.00" intervalHaltingDurationSum="0.00" startedHalts="0.00" meanVehicleNumber="0.00" maxVehicleNumber="0" />
   <interval begin="0.00" end="300.00" id="feitianlu_second_north_entry1" sampledSeconds="104.57" nVehEntered="10" nVehLeft="10" nVehSeen="10" meanSpeed="10.82" meanTimeLoss="1.48" meanOccupancy="0.91" maxOccupancy="13.45" meanMaxJamLengthInVehicles="0.00" meanMaxJamLengthInMeters="0.03" maxJamLengthInVehicles="1" maxJamLengthInMeters="8.38" jamLengthInVehiclesSum="1" jamLengthInMetersSum="8.38" meanHaltingDuration="2.00" maxHaltingDuration="2.00" haltingDurationSum="2.00" meanIntervalHaltingDuration="2.00" maxIntervalHaltingDuration="2.00" intervalHaltingDurationSum="2.00" startedHalts="1.00" meanVehicleNumber="0.37" maxVehicleNumber="5" />
   <interval begin="0.00" end="300.00" id="feitianlu_second_north_entry2" sampledSeconds="92.95" nVehEntered="9" nVehLeft="9" nVehSeen="9" meanSpeed="12.58" meanTimeLoss="0.56" meanOccupancy="0.81" maxOccupancy="8.07" meanMaxJamLengthInVehicles="0.00" meanMaxJamLengthInMeters="0.00" maxJamLengthInVehicles="0" maxJamLengthInMeters="0.00" jamLengthInVehiclesSum="0" jamLengthInMetersSum="0.00" meanHaltingDuration="0.00" maxHaltingDuration="0.00" haltingDurationSum="0.00" meanIntervalHaltingDuration="0.00" maxIntervalHaltingDuration="0.00" intervalHaltingDurationSum="0.00" startedHalts="0.00" meanVehicleNumber="0.33" maxVehicleNumber="4" />
   <interval begin="0.00" end="300.00" id="feitianlu_second_north_exit0" sampledSeconds="0.00" nVehEntered="0" nVehLeft="0" nVehSeen="0" meanSpeed="-1.00" meanTimeLoss="-1.00" meanOccupancy="0.00" maxOccupancy="0.00" meanMaxJamLengthInVehicles="0.00" meanMaxJamLengthInMeters="0.00" maxJamLengthInVehicles="0" maxJamLengthInMeters="0.00" jamLengthInVehiclesSum="0" jamLengthInMetersSum="0.00" meanHaltingDuration="0.00" maxHaltingDuration="0.00" haltingDurationSum="0.00" meanIntervalHaltingDuration="0.00" maxIntervalHaltingDuration="0.00" intervalHaltingDurationSum="0.00" startedHalts="0.00" meanVehicleNumber="0.00" maxVehicleNumber="0" />
   <interval begin="0.00" end="300.00" id="feitianlu_second_north_exit1" sampledSeconds="32.20" nVehEntered="2" nVehLeft="2" nVehSeen="2" meanSpeed="11.85" meanTimeLoss="1.43" meanOccupancy="0.28" maxOccupancy="2.69" meanMaxJamLengthInVehicles="0.00" meanMaxJamLengthInMeters="0.00" maxJamLengthInVehicles="0" maxJamLengthInMeters="0.00" jamLengthInVehiclesSum="0" jamLengthInMetersSum="0.00" meanHaltingDuration="0.00" maxHaltingDuration="0.00" haltingDurationSum="0.00" meanIntervalHaltingDuration="0.00" maxIntervalHaltingDuration="0.00" intervalHaltingDurationSum="0.00" startedHalts="0.00" meanVehicleNumber="0.11" maxVehicleNumber="1" />
   <interval begin="0.00" end="300.00" id="feitianlu_second_north_exit2" sampledSeconds="122.02" nVehEntered="2" nVehLeft="2" nVehSeen="2" meanSpeed="3.04" meanTimeLoss="46.98" meanOccupancy="1.09" maxOccupancy="5.38" meanMaxJamLengthInVehicles="0.28" meanMaxJamLengthInMeters="1.40" maxJamLengthInVehicles="1" maxJamLengthInMeters="5.00" jamLengthInVehiclesSum="84" jamLengthInMetersSum="420.00" meanHaltingDuration="43.00" maxHaltingDuration="85.00" haltingDurationSum="86.00" meanIntervalHaltingDuration="43.00" maxIntervalHaltingDuration="85.00" intervalHaltingDurationSum="86.00" startedHalts="2.00" meanVehicleNumber="0.41" maxVehicleNumber="2" />
   <interval begin="0.00" end="300.00" id="feitianlu_second_south_entry0" sampledSeconds="0.00" nVehEntered="0" nVehLeft="0" nVehSeen="0" meanSpeed="-1.00" meanTimeLoss="-1.00" meanOccupancy="0.00" maxOccupancy="0.00" meanMaxJamLengthInVehicles="0.00" meanMaxJamLengthInMeters="0.00" maxJamLengthInVehicles="0" maxJamLengthInMeters="0.00" jamLengthInVehiclesSum="0" jamLengthInMetersSum="0.00" meanHaltingDuration="0.00" maxHaltingDuration="0.00" haltingDurationSum="0.00" meanIntervalHaltingDuration="0.00" maxIntervalHaltingDuration="0.00" intervalHaltingDurationSum="0.00" startedHalts="0.00" meanVehicleNumber="0.00" maxVehicleNumber="0" />
   <interval begin="0.00" end="300.00" id="feitianlu_second_south_entry1" sampledSeconds="166.97" nVehEntered="6" nVehLeft="6" nVehSeen="6" meanSpeed="6.59" meanTimeLoss="13.19" meanOccupancy="1.64" maxOccupancy="4.81" meanMaxJamLengthInVehicles="0.16" meanMaxJamLengthInMeters="0.97" maxJamLengthInVehicles="1" maxJamLengthInMeters="7.10" jamLengthInVehiclesSum="49" jamLengthInMetersSum="291.20" meanHaltingDuration="17.33" maxHaltingDuration="28.00" haltingDurationSum="52.00" meanIntervalHaltingDuration="17.33" maxIntervalHaltingDuration="28.00" intervalHaltingDurationSum="52.00" startedHalts="3.00" meanVehicleNumber="0.56" maxVehicleNumber="2" />
   <interval begin="0.00" end="300.00" id="feitianlu_second_south_entry2" sampledSeconds="325.84" nVehEntered="8" nVehLeft="7" nVehSeen="8" meanSpeed="4.03" meanTimeLoss="28.06" meanOccupancy="2.92" maxOccupancy="8.17" meanMaxJamLengthInVehicles="0.59" meanMaxJamLengthInMeters="3.45" maxJamLengthInVehicles="3" maxJamLengthInMeters="20.03" jamLengthInVehiclesSum="177" jamLengthInMetersSum="1036.29" meanHaltingDuration="36.40" maxHaltingDuration="79.00" haltingDurationSum="182.00" meanIntervalHaltingDuration="36.40" maxIntervalHaltingDuration="79.00" intervalHaltingDurationSum="182.00" startedHalts="5.00" meanVehicleNumber="1.10" maxVehicleNumber="3" />
   <interval begin="0.00" end="300.00" id="feitianlu_second_south_exit0" sampledSeconds="0.00" nVehEntered="0" nVehLeft="0" nVehSeen="0" meanSpeed="-1.00" meanTimeLoss="-1.00" meanOccupancy="0.00" maxOccupancy="0.00" meanMaxJamLengthInVehicles="0.00" meanMaxJamLengthInMeters="0.00" maxJamLengthInVehicles="0" maxJamLengthInMeters="0.00" jamLengthInVehiclesSum="0" jamLengthInMetersSum="0.00" meanHaltingDuration="0.00" maxHaltingDuration="0.00" haltingDurationSum="0.00" meanIntervalHaltingDuration="0.00" maxIntervalHaltingDuration="0.00" intervalHaltingDurationSum="0.00" startedHalts="0.00" meanVehicleNumber="0.00" maxVehicleNumber="0" />
   <interval begin="0.00" end="300.00" id="feitianlu_second_south_exit1" sampledSeconds="0.00" nVehEntered="0" nVehLeft="0" nVehSeen="0" meanSpeed="-1.00" meanTimeLoss="-1.00" meanOccupancy="0.00" maxOccupancy="0.00" meanMaxJamLengthInVehicles="0.00" meanMaxJamLengthInMeters="0.00" maxJamLengthInVehicles="0" maxJamLengthInMeters="0.00" jamLengthInVehiclesSum="0" jamLengthInMetersSum="0.00" meanHaltingDuration="0.00" maxHaltingDuration="0.00" haltingDurationSum="0.00" meanIntervalHaltingDuration="0.00" maxIntervalHaltingDuration="0.00" intervalHaltingDurationSum="0.00" startedHalts="0.00" meanVehicleNumber="0.00" maxVehicleNumber="0" />
   <interval begin="0.00" end="300.00" id="feitianlu_second_south_exit2" sampledSeconds="94.53" nVehEntered="6" nVehLeft="6" nVehSeen="6" meanSpeed="11.60" meanTimeLoss="1.84" meanOccupancy="0.86" maxOccupancy="13.97" meanMaxJamLengthInVehicles="0.00" meanMaxJamLengthInMeters="0.00" maxJamLengthInVehicles="0" maxJamLengthInMeters="0.00" jamLengthInVehiclesSum="0" jamLengthInMetersSum="0.00" meanHaltingDuration="0.00" maxHaltingDuration="0.00" haltingDurationSum="0.00" meanIntervalHaltingDuration="0.00" maxIntervalHaltingDuration="0.00" intervalHaltingDurationSum="0.00" startedHalts="0.00" meanVehicleNumber="0.33" maxVehicleNumber="5" />
</detector>
